lab_03/part1/FA.v
module FA (
    a,
    b,
    cin,
    cout,
    sum
);
    input a, b, cin;
    output cout, sum;

    assign cout = a & b | a & cin | b & cin;
    assign sum  = a ^ b ^ cin;
endmodule

lab_02/RCA.v
module RCA(a, b, cout, sum);
	input [3:0] a, b;
	output [3:0] sum;
	output cout;

	wire [4:0] c;
	genvar i;
	generate
		for(i = 0 ; i < 4 ; i = i + 1)begin
			FA fa(a[i],b[i],c[i],c[i+1],sum[i]);
		end
	endgenerate
	assign cout = c[4];
	assign c[0] = 0;
endmodule

lab_02/TM.v
`timescale 1ns/1ps
module TM;

reg [3:0] a, b;
wire cout;
wire [3:0] sum;
wire cor;
integer i,j;

assign cor = (i+j) == {cout,sum};
initial
	begin
		$dumpfile("test.vcd");
		$dumpvars(0, rca);
		$monitor("a = %d, b = %d | cout = %b sum = %d | correct!! = %b", a, b, cout, sum, cor);
		for(i = 0 ; i < 16 ; i = i + 1)begin
			a <= i;
			for(j = 0 ; j < 16 ; j = j + 1)begin
				b <= j;
				#10;
			end

		end
		$finish;

	end
	RCA rca(a,b,cout,sum);
endmodule

lab_02/test.vcd
$date
	Tue Mar 21 12:34:32 2023
$end
$version
	Icarus Verilog
$end
$timescale
	1ps
$end
$scope module TM $end
$scope module rca $end
$var wire 4 ! a [3:0] $end
$var wire 4 " b [3:0] $end
$var wire 4 # sum [3:0] $end
$var wire 1 $ cout $end
$var wire 5 % c [4:0] $end
$scope begin genblk1[0] $end
$var parameter 2 & i $end
$scope module fa $end
$var wire 1 ' a $end
$var wire 1 ( b $end
$var wire 1 ) cin $end
$var wire 1 * sum $end
$var wire 1 + cout $end
$upscope $end
$upscope $end
$scope begin genblk1[1] $end
$var parameter 2 , i $end
$scope module fa $end
$var wire 1 - a $end
$var wire 1 . b $end
$var wire 1 / cin $end
$var wire 1 0 sum $end
$var wire 1 1 cout $end
$upscope $end
$upscope $end
$scope begin genblk1[2] $end
$var parameter 3 2 i $end
$scope module fa $end
$var wire 1 3 a $end
$var wire 1 4 b $end
$var wire 1 5 cin $end
$var wire 1 6 sum $end
$var wire 1 7 cout $end
$upscope $end
$upscope $end
$scope begin genblk1[3] $end
$var parameter 3 8 i $end
$scope module fa $end
$var wire 1 9 a $end
$var wire 1 : b $end
$var wire 1 ; cin $end
$var wire 1 < sum $end
$var wire 1 = cout $end
$upscope $end
$upscope $end
$upscope $end
$upscope $end
$enddefinitions $end
$comment Show the parameter values. $end
$dumpall
b11 8
b10 2
b1 ,
b0 &
$end
#0
$dumpvars
0=
0<
0;
0:
09
07
06
05
04
03
01
00
0/
0.
0-
0+
0*
0)
0(
0'
b0 %
0$
b0 #
b0 "
b0 !
$end
#10000
b1 #
1*
1(
b1 "
#20000
0*
b10 #
10
0(
1.
b10 "
#30000
b11 #
1*
1(
b11 "
#40000
0*
00
b100 #
16
0(
0.
14
b100 "
#50000
b101 #
1*
1(
b101 "
#60000
0*
b110 #
10
0(
1.
b110 "
#70000
b111 #
1*
1(
b111 "
#80000
0*
00
06
b1000 #
1<
0(
0.
04
1:
b1000 "
#90000
b1001 #
1*
1(
b1001 "
#100000
0*
b1010 #
10
0(
1.
b1010 "
#110000
b1011 #
1*
1(
b1011 "
#120000
0*
00
b1100 #
16
0(
0.
14
b1100 "
#130000
b1101 #
1*
1(
b1101 "
#140000
0*
b1110 #
10
0(
1.
b1110 "
#150000
b1111 #
1*
1(
b1111 "
#160000
00
06
b1 #
0<
0(
0.
04
0:
1'
b0 "
b1 !
#170000
10
1/
b10 #
0*
b10 %
1+
1(
b1 "
#180000
06
0/
05
1*
0+
b11 #
10
b0 %
01
0(
1.
b10 "
#190000
16
15
00
11
1/
b100 #
0*
b110 %
1+
1(
b11 "
#200000
0<
0/
05
0;
1*
0+
00
01
b101 #
16
b0 %
07
0(
0.
14
b100 "
#210000
10
1/
b110 #
0*
b10 %
1+
1(
b101 "
#220000
0<
0;
16
07
0/
05
1*
0+
b111 #
10
b0 %
01
0(
1.
b110 "
#230000
1<
1;
06
17
15
00
11
1/
b1000 #
0*
b1110 %
1+
1(
b111 "
#240000
0/
05
0;
0$
1*
0+
00
01
06
07
b1001 #
1<
b0 %
0=
0(
0.
04
1:
b1000 "
#250000
10
1/
b1010 #
0*
b10 %
1+
1(
b1001 "
#260000
06
0/
05
1*
0+
b1011 #
10
b0 %
01
0(
1.
b1010 "
#270000
16
15
00
11
1/
b1100 #
0*
b110 %
1+
1(
b1011 "
#280000
0$
1<
0=
0/
05
0;
1*
0+
00
01
b1101 #
16
b0 %
07
0(
0.
14
b1100 "
#290000
10
1/
b1110 #
0*
b10 %
1+
1(
b1101 "
#300000
0$
1<
0=
0;
16
07
0/
05
1*
0+
b1111 #
10
b0 %
01
0(
1.
b1110 "
#310000
1$
0<
1=
1;
06
17
15
00
11
1/
b0 #
0*
b11110 %
1+
1(
b1111 "
#320000
05
10
01
0;
0$
0/
06
07
b10 #
0<
0=
b0 %
0+
0(
0.
04
0:
0'
1-
b0 "
b10 !
#330000
b11 #
1*
1(
b1 "
#340000
16
15
0*
b100 #
00
b100 %
11
0(
1.
b10 "
#350000
b101 #
1*
1(
b11 "
#360000
0<
05
0;
0*
10
01
b110 #
16
b0 %
07
0(
0.
14
b100 "
#370000
b111 #
1*
1(
b101 "
#380000
1<
1;
06
17
15
0*
b1000 #
00
b1100 %
11
0(
1.
b110 "
#390000
b1001 #
1*
1(
b111 "
#400000
05
0;
0$
0*
10
01
06
07
b1010 #
1<
b0 %
0=
0(
0.
04
1:
b1000 "
#410000
b1011 #
1*
1(
b1001 "
#420000
16
15
0*
b1100 #
00
b100 %
11
0(
1.
b1010 "
#430000
b1101 #
1*
1(
b1011 "
#440000
0$
1<
0=
05
0;
0*
10
01
b1110 #
16
b0 %
07
0(
0.
14
b1100 "
#450000
b1111 #
1*
1(
b1101 "
#460000
1$
0<
1=
1;
06
17
15
0*
b0 #
00
b11100 %
11
0(
1.
b1110 "
#470000
b1 #
1*
1(
b1111 "
#480000
05
0;
0$
10
01
06
07
b11 #
0<
b0 %
0=
0(
0.
04
0:
1'
b0 "
b11 !
#490000
16
15
00
11
1/
b100 #
0*
b110 %
1+
1(
b1 "
#500000
0/
1*
b100 %
0+
b101 #
00
0(
1.
b10 "
#510000
10
1/
b110 #
0*
b110 %
1+
1(
b11 "
#520000
05
01
0<
0/
0;
1*
0+
10
b111 #
16
b0 %
07
0(
0.
14
b100 "
#530000
1<
1;
06
17
15
00
11
1/
b1000 #
0*
b1110 %
1+
1(
b101 "
#540000
0/
1*
b1100 %
0+
b1001 #
00
0(
1.
b110 "
#550000
10
1/
b1010 #
0*
b1110 %
1+
1(
b111 "
#560000
05
01
0/
0;
0$
1*
0+
10
06
07
b1011 #
1<
b0 %
0=
0(
0.
04
1:
b1000 "
#570000
16
15
00
11
1/
b1100 #
0*
b110 %
1+
1(
b1001 "
#580000
0/
1*
b100 %
0+
b1101 #
00
0(
1.
b1010 "
#590000
10
1/
b1110 #
0*
b110 %
1+
1(
b1011 "
#600000
05
0$
01
1<
0=
0/
0;
1*
0+
10
b1111 #
16
b0 %
07
0(
0.
14
b1100 "
#610000
1$
0<
1=
1;
06
17
15
00
11
1/
b0 #
0*
b11110 %
1+
1(
b1101 "
#620000
0/
1*
b11100 %
0+
b1 #
00
0(
1.
b1110 "
#630000
10
1/
b10 #
0*
b11110 %
1+
1(
b1111 "
#640000
0;
16
07
00
05
0$
0/
01
b100 #
0<
0=
b0 %
0+
0(
0.
04
0:
0'
0-
13
b0 "
b100 !
#650000
b101 #
1*
1(
b1 "
#660000
0*
b110 #
10
0(
1.
b10 "
#670000
b111 #
1*
1(
b11 "
#680000
1<
1;
0*
00
b1000 #
06
b1000 %
17
0(
0.
14
b100 "
#690000
b1001 #
1*
1(
b101 "
#700000
0*
b1010 #
10
0(
1.
b110 "
#710000
b1011 #
1*
1(
b111 "
#720000
0;
0$
0*
00
16
07
b1100 #
1<
b0 %
0=
0(
0.
04
1:
b1000 "
#730000
b1101 #
1*
1(
b1001 "
#740000
0*
b1110 #
10
0(
1.
b1010 "
#750000
b1111 #
1*
1(
b1011 "
#760000
1$
0<
1=
1;
0*
00
b0 #
06
b11000 %
17
0(
0.
14
b1100 "
#770000
b1 #
1*
1(
b1101 "
#780000
0*
b10 #
10
0(
1.
b1110 "
#790000
b11 #
1*
1(
b1111 "
#800000
0;
0$
00
16
07
b101 #
0<
b0 %
0=
0(
0.
04
0:
1'
b0 "
b101 !
#810000
10
1/
b110 #
0*
b10 %
1+
1(
b1 "
#820000
0<
0;
16
07
0/
05
1*
0+
b111 #
10
b0 %
01
0(
1.
b10 "
#830000
1<
1;
06
17
15
00
11
1/
b1000 #
0*
b1110 %
1+
1(
b11 "
#840000
0/
05
1*
0+
00
b1000 %
01
b1001 #
06
0(
0.
14
b100 "
#850000
10
1/
b1010 #
0*
b1010 %
1+
1(
b101 "
#860000
06
0/
05
1*
0+
b1011 #
10
b1000 %
01
0(
1.
b110 "
#870000
16
15
00
11
1/
b1100 #
0*
b1110 %
1+
1(
b111 "
#880000
0;
07
0/
05
0$
1*
0+
00
01
16
b1101 #
1<
b0 %
0=
0(
0.
04
1:
b1000 "
#890000
10
1/
b1110 #
0*
b10 %
1+
1(
b1001 "
#900000
0$
1<
0=
0;
16
07
0/
05
1*
0+
b1111 #
10
b0 %
01
0(
1.
b1010 "
#910000
1$
0<
1=
1;
06
17
15
00
11
1/
b0 #
0*
b11110 %
1+
1(
b1011 "
#920000
0/
05
1*
0+
00
b11000 %
01
b1 #
06
0(
0.
14
b1100 "
#930000
10
1/
b10 #
0*
b11010 %
1+
1(
b1101 "
#940000
06
0/
05
1*
0+
b11 #
10
b11000 %
01
0(
1.
b1110 "
#950000
16
15
00
11
1/
b100 #
0*
b11110 %
1+
1(
b1111 "
#960000
0;
07
05
10
01
0$
0/
16
b110 #
0<
0=
b0 %
0+
0(
0.
04
0:
0'
1-
b0 "
b110 !
#970000
b111 #
1*
1(
b1 "
#980000
1<
1;
06
17
15
0*
b1000 #
00
b1100 %
11
0(
1.
b10 "
#990000
b1001 #
1*
1(
b11 "
#1000000
05
0*
10
b1000 %
01
b1010 #
06
0(
0.
14
b100 "
#1010000
b1011 #
1*
1(
b101 "
#1020000
16
15
0*
b1100 #
00
b1100 %
11
0(
1.
b110 "
#1030000
b1101 #
1*
1(
b111 "
#1040000
0;
07
05
0$
0*
10
01
16
b1110 #
1<
b0 %
0=
0(
0.
04
1:
b1000 "
#1050000
b1111 #
1*
1(
b1001 "
#1060000
1$
0<
1=
1;
06
17
15
0*
b0 #
00
b11100 %
11
0(
1.
b1010 "
#1070000
b1 #
1*
1(
b1011 "
#1080000
05
0*
10
b11000 %
01
b10 #
06
0(
0.
14
b1100 "
#1090000
b11 #
1*
1(
b1101 "
#1100000
16
15
0*
b100 #
00
b11100 %
11
0(
1.
b1110 "
#1110000
b101 #
1*
1(
b1111 "
#1120000
0;
07
05
0$
10
01
16
b111 #
0<
b0 %
0=
0(
0.
04
0:
1'
b0 "
b111 !
#1130000
1<
1;
06
17
15
00
11
1/
b1000 #
0*
b1110 %
1+
1(
b1 "
#1140000
0/
1*
b1100 %
0+
b1001 #
00
0(
1.
b10 "
#1150000
10
1/
b1010 #
0*
b1110 %
1+
1(
b11 "
#1160000
05
01
0/
1*
b1000 %
0+
10
b1011 #
06
0(
0.
14
b100 "
#1170000
16
15
00
11
1/
b1100 #
0*
b1110 %
1+
1(
b101 "
#1180000
0/
1*
b1100 %
0+
b1101 #
00
0(
1.
b110 "
#1190000
10
1/
b1110 #
0*
b1110 %
1+
1(
b111 "
#1200000
0;
07
05
01
0/
0$
1*
0+
10
16
b1111 #
1<
b0 %
0=
0(
0.
04
1:
b1000 "
#1210000
1$
0<
1=
1;
06
17
15
00
11
1/
b0 #
0*
b11110 %
1+
1(
b1001 "
#1220000
0/
1*
b11100 %
0+
b1 #
00
0(
1.
b1010 "
#1230000
10
1/
b10 #
0*
b11110 %
1+
1(
b1011 "
#1240000
05
01
0/
1*
b11000 %
0+
10
b11 #
06
0(
0.
14
b1100 "
#1250000
16
15
00
11
1/
b100 #
0*
b11110 %
1+
1(
b1101 "
#1260000
0/
1*
b11100 %
0+
b101 #
00
0(
1.
b1110 "
#1270000
10
1/
b110 #
0*
b11110 %
1+
1(
b1111 "
#1280000
0$
06
1<
0=
b1000 #
00
05
0;
0/
01
07
b0 %
0+
0(
0.
04
0:
0'
0-
03
19
b0 "
b1000 !
#1290000
b1001 #
1*
1(
b1 "
#1300000
0*
b1010 #
10
0(
1.
b10 "
#1310000
b1011 #
1*
1(
b11 "
#1320000
0*
00
b1100 #
16
0(
0.
14
b100 "
#1330000
b1101 #
1*
1(
b101 "
#1340000
0*
b1110 #
10
0(
1.
b110 "
#1350000
b1111 #
1*
1(
b111 "
#1360000
1$
0*
00
06
b0 #
0<
b10000 %
1=
0(
0.
04
1:
b1000 "
#1370000
b1 #
1*
1(
b1001 "
#1380000
0*
b10 #
10
0(
1.
b1010 "
#1390000
b11 #
1*
1(
b1011 "
#1400000
0*
00
b100 #
16
0(
0.
14
b1100 "
#1410000
b101 #
1*
1(
b1101 "
#1420000
0*
b110 #
10
0(
1.
b1110 "
#1430000
b111 #
1*
1(
b1111 "
#1440000
0$
00
06
b1001 #
1<
b0 %
0=
0(
0.
04
0:
1'
b0 "
b1001 !
#1450000
10
1/
b1010 #
0*
b10 %
1+
1(
b1 "
#1460000
06
0/
05
1*
0+
b1011 #
10
b0 %
01
0(
1.
b10 "
#1470000
16
15
00
11
1/
b1100 #
0*
b110 %
1+
1(
b11 "
#1480000
0$
1<
0=
0/
05
0;
1*
0+
00
01
b1101 #
16
b0 %
07
0(
0.
14
b100 "
#1490000
10
1/
b1110 #
0*
b10 %
1+
1(
b101 "
#1500000
0$
1<
0=
0;
16
07
0/
05
1*
0+
b1111 #
10
b0 %
01
0(
1.
b110 "
#1510000
1$
0<
1=
1;
06
17
15
00
11
1/
b0 #
0*
b11110 %
1+
1(
b111 "
#1520000
0/
05
0;
1*
0+
00
01
06
b10000 %
07
b1 #
0<
0(
0.
04
1:
b1000 "
#1530000
10
1/
b10 #
0*
b10010 %
1+
1(
b1001 "
#1540000
06
0/
05
1*
0+
b11 #
10
b10000 %
01
0(
1.
b1010 "
#1550000
16
15
00
11
1/
b100 #
0*
b10110 %
1+
1(
b1011 "
#1560000
0<
0/
05
0;
1*
0+
00
01
b101 #
16
b10000 %
07
0(
0.
14
b1100 "
#1570000
10
1/
b110 #
0*
b10010 %
1+
1(
b1101 "
#1580000
0<
0;
16
07
0/
05
1*
0+
b111 #
10
b10000 %
01
0(
1.
b1110 "
#1590000
1<
1;
06
17
15
00
11
1/
b1000 #
0*
b11110 %
1+
1(
b1111 "
#1600000
0$
05
0=
10
01
0;
0/
06
07
b1010 #
1<
b0 %
0+
0(
0.
04
0:
0'
1-
b0 "
b1010 !
#1610000
b1011 #
1*
1(
b1 "
#1620000
16
15
0*
b1100 #
00
b100 %
11
0(
1.
b10 "
#1630000
b1101 #
1*
1(
b11 "
#1640000
0$
1<
0=
05
0;
0*
10
01
b1110 #
16
b0 %
07
0(
0.
14
b100 "
#1650000
b1111 #
1*
1(
b101 "
#1660000
1$
0<
1=
1;
06
17
15
0*
b0 #
00
b11100 %
11
0(
1.
b110 "
#1670000
b1 #
1*
1(
b111 "
#1680000
05
0;
0*
10
01
06
b10000 %
07
b10 #
0<
0(
0.
04
1:
b1000 "
#1690000
b11 #
1*
1(
b1001 "
#1700000
16
15
0*
b100 #
00
b10100 %
11
0(
1.
b1010 "
#1710000
b101 #
1*
1(
b1011 "
#1720000
0<
05
0;
0*
10
01
b110 #
16
b10000 %
07
0(
0.
14
b1100 "
#1730000
b111 #
1*
1(
b1101 "
#1740000
1<
1;
06
17
15
0*
b1000 #
00
b11100 %
11
0(
1.
b1110 "
#1750000
b1001 #
1*
1(
b1111 "
#1760000
0$
0=
05
0;
10
01
06
b0 %
07
b1011 #
1<
0(
0.
04
0:
1'
b0 "
b1011 !
#1770000
16
15
00
11
1/
b1100 #
0*
b110 %
1+
1(
b1 "
#1780000
0/
1*
b100 %
0+
b1101 #
00
0(
1.
b10 "
#1790000
10
1/
b1110 #
0*
b110 %
1+
1(
b11 "
#1800000
05
0$
01
1<
0=
0/
0;
1*
0+
10
b1111 #
16
b0 %
07
0(
0.
14
b100 "
#1810000
1$
0<
1=
1;
06
17
15
00
11
1/
b0 #
0*
b11110 %
1+
1(
b101 "
#1820000
0/
1*
b11100 %
0+
b1 #
00
0(
1.
b110 "
#1830000
10
1/
b10 #
0*
b11110 %
1+
1(
b111 "
#1840000
05
01
0/
0;
1*
0+
10
06
b10000 %
07
b11 #
0<
0(
0.
04
1:
b1000 "
#1850000
16
15
00
11
1/
b100 #
0*
b10110 %
1+
1(
b1001 "
#1860000
0/
1*
b10100 %
0+
b101 #
00
0(
1.
b1010 "
#1870000
10
1/
b110 #
0*
b10110 %
1+
1(
b1011 "
#1880000
05
01
0<
0/
0;
1*
0+
10
b111 #
16
b10000 %
07
0(
0.
14
b1100 "
#1890000
1<
1;
06
17
15
00
11
1/
b1000 #
0*
b11110 %
1+
1(
b1101 "
#1900000
0/
1*
b11100 %
0+
b1001 #
00
0(
1.
b1110 "
#1910000
10
1/
b1010 #
0*
b11110 %
1+
1(
b1111 "
#1920000
0$
0=
0;
16
07
00
05
0/
01
b1100 #
1<
b0 %
0+
0(
0.
04
0:
0'
0-
13
b0 "
b1100 !
#1930000
b1101 #
1*
1(
b1 "
#1940000
0*
b1110 #
10
0(
1.
b10 "
#1950000
b1111 #
1*
1(
b11 "
#1960000
1$
0<
1=
1;
0*
00
b0 #
06
b11000 %
17
0(
0.
14
b100 "
#1970000
b1 #
1*
1(
b101 "
#1980000
0*
b10 #
10
0(
1.
b110 "
#1990000
b11 #
1*
1(
b111 "
#2000000
0;
0*
00
16
b10000 %
07
b100 #
0<
0(
0.
04
1:
b1000 "
#2010000
b101 #
1*
1(
b1001 "
#2020000
0*
b110 #
10
0(
1.
b1010 "
#2030000
b111 #
1*
1(
b1011 "
#2040000
1<
1;
0*
00
b1000 #
06
b11000 %
17
0(
0.
14
b1100 "
#2050000
b1001 #
1*
1(
b1101 "
#2060000
0*
b1010 #
10
0(
1.
b1110 "
#2070000
b1011 #
1*
1(
b1111 "
#2080000
0$
0=
0;
00
16
b0 %
07
b1101 #
1<
0(
0.
04
0:
1'
b0 "
b1101 !
#2090000
10
1/
b1110 #
0*
b10 %
1+
1(
b1 "
#2100000
0$
1<
0=
0;
16
07
0/
05
1*
0+
b1111 #
10
b0 %
01
0(
1.
b10 "
#2110000
1$
0<
1=
1;
06
17
15
00
11
1/
b0 #
0*
b11110 %
1+
1(
b11 "
#2120000
0/
05
1*
0+
00
b11000 %
01
b1 #
06
0(
0.
14
b100 "
#2130000
10
1/
b10 #
0*
b11010 %
1+
1(
b101 "
#2140000
06
0/
05
1*
0+
b11 #
10
b11000 %
01
0(
1.
b110 "
#2150000
16
15
00
11
1/
b100 #
0*
b11110 %
1+
1(
b111 "
#2160000
0;
07
0/
05
1*
0+
00
b10000 %
01
16
b101 #
0<
0(
0.
04
1:
b1000 "
#2170000
10
1/
b110 #
0*
b10010 %
1+
1(
b1001 "
#2180000
0<
0;
16
07
0/
05
1*
0+
b111 #
10
b10000 %
01
0(
1.
b1010 "
#2190000
1<
1;
06
17
15
00
11
1/
b1000 #
0*
b11110 %
1+
1(
b1011 "
#2200000
0/
05
1*
0+
00
b11000 %
01
b1001 #
06
0(
0.
14
b1100 "
#2210000
10
1/
b1010 #
0*
b11010 %
1+
1(
b1101 "
#2220000
06
0/
05
1*
0+
b1011 #
10
b11000 %
01
0(
1.
b1110 "
#2230000
16
15
00
11
1/
b1100 #
0*
b11110 %
1+
1(
b1111 "
#2240000
0$
0=
0;
07
05
10
01
0/
16
b1110 #
1<
b0 %
0+
0(
0.
04
0:
0'
1-
b0 "
b1110 !
#2250000
b1111 #
1*
1(
b1 "
#2260000
1$
0<
1=
1;
06
17
15
0*
b0 #
00
b11100 %
11
0(
1.
b10 "
#2270000
b1 #
1*
1(
b11 "
#2280000
05
0*
10
b11000 %
01
b10 #
06
0(
0.
14
b100 "
#2290000
b11 #
1*
1(
b101 "
#2300000
16
15
0*
b100 #
00
b11100 %
11
0(
1.
b110 "
#2310000
b101 #
1*
1(
b111 "
#2320000
0;
07
05
0*
10
b10000 %
01
16
b110 #
0<
0(
0.
04
1:
b1000 "
#2330000
b111 #
1*
1(
b1001 "
#2340000
1<
1;
06
17
15
0*
b1000 #
00
b11100 %
11
0(
1.
b1010 "
#2350000
b1001 #
1*
1(
b1011 "
#2360000
05
0*
10
b11000 %
01
b1010 #
06
0(
0.
14
b1100 "
#2370000
b1011 #
1*
1(
b1101 "
#2380000
16
15
0*
b1100 #
00
b11100 %
11
0(
1.
b1110 "
#2390000
b1101 #
1*
1(
b1111 "
#2400000
0$
0=
0;
07
05
10
b0 %
01
16
b1111 #
1<
0(
0.
04
0:
1'
b0 "
b1111 !
#2410000
1$
0<
1=
1;
06
17
15
00
11
1/
b0 #
0*
b11110 %
1+
1(
b1 "
#2420000
0/
1*
b11100 %
0+
b1 #
00
0(
1.
b10 "
#2430000
10
1/
b10 #
0*
b11110 %
1+
1(
b11 "
#2440000
05
01
0/
1*
b11000 %
0+
10
b11 #
06
0(
0.
14
b100 "
#2450000
16
15
00
11
1/
b100 #
0*
b11110 %
1+
1(
b101 "
#2460000
0/
1*
b11100 %
0+
b101 #
00
0(
1.
b110 "
#2470000
10
1/
b110 #
0*
b11110 %
1+
1(
b111 "
#2480000
0;
07
05
01
0/
1*
b10000 %
0+
10
16
b111 #
0<
0(
0.
04
1:
b1000 "
#2490000
1<
1;
06
17
15
00
11
1/
b1000 #
0*
b11110 %
1+
1(
b1001 "
#2500000
0/
1*
b11100 %
0+
b1001 #
00
0(
1.
b1010 "
#2510000
10
1/
b1010 #
0*
b11110 %
1+
1(
b1011 "
#2520000
05
01
0/
1*
b11000 %
0+
10
b1011 #
06
0(
0.
14
b1100 "
#2530000
16
15
00
11
1/
b1100 #
0*
b11110 %
1+
1(
b1101 "
#2540000
0/
1*
b11100 %
0+
b1101 #
00
0(
1.
b1110 "
#2550000
10
1/
b1110 #
0*
b11110 %
1+
1(
b1111 "
