lab_03/part1/FA.v
module FA (
    a,
    b,
    cin,
    cout,
    sum
);
    input a, b, cin;
    output cout, sum;

    assign cout = a & b | a & cin | b & cin;
    assign sum  = a ^ b ^ cin;
endmodule

lab_01/TM.v
`timescale 1ns/1ps
module TM;

reg a, b, cin;
wire cout, sum;

initial
	begin
		$dumpfile("test.vcd");
		$dumpvars(0, fa);
		$monitor("a = %b, b = %b cin = %b | cout = %b sum = %b ", a, b, cin, cout, sum);
		#10 a=1'b0; b=1'b0; cin=1'b0;
		#10 a=1'b0; b=1'b1; cin=1'b0;
		#10 a=1'b1; b=1'b0; cin=1'b0;
		#10 a=1'b1; b=1'b1; cin=1'b0;
		#10 a=1'b0; b=1'b0; cin=1'b1;
		#10 a=1'b0; b=1'b1; cin=1'b1;
		#10 a=1'b1; b=1'b0; cin=1'b1;
		#10 a=1'b1; b=1'b1; cin=1'b1;
		#10 $finish;
	end
	FA fa( a, b, cin, cout, sum );
endmodule

lab_01/test.vcd
$date
	Tue Mar 14 13:12:54 2023
$end
$version
	Icarus Verilog
$end
$timescale
	1ps
$end
$scope module TM $end
$scope module fa $end
$var wire 1 ! a $end
$var wire 1 " b $end
$var wire 1 # cin $end
$var wire 1 $ sum $end
$var wire 1 % cout $end
$upscope $end
$upscope $end
$enddefinitions $end
$comment Show the parameter values. $end
$dumpall
$end
#0
$dumpvars
x%
x$
x#
x"
x!
$end
#10000
0$
0%
0#
0"
0!
#20000
1$
1"
#30000
0"
1!
#40000
0$
1%
1"
#50000
1$
0%
1#
0"
0!
#60000
0$
1%
1"
#70000
0"
1!
#80000
1$
1"
