邏輯設計實驗/二/2/AddSub4.v
module AddSub4 (
    a,
    b,
    sel,
    cout,
    sum
);
    input [3:0] a, b;
    input sel;
    output [3:0] sum;
    output cout;

    assign {cout, sum} = sel ? {1'b0, a} + {1'b0, b ^ 4'b1111} + 1 : {1'b0, a} + {1'b0, b};
endmodule

邏輯設計實驗/二/1/TM_AddSub4.v
`timescale 1ns / 1ps
module TM_AddSub4;

    reg [3:0] a, b;
    reg sel;
    wire cout;
    wire [3:0] sum;
    wire cor;
    integer i, j;

    assign cor = (i + j) == {cout, sum};
    initial begin
        $dumpfile("test.vcd");
        $dumpvars(0, AddSub4);
        //$monitor("a = %d, b = %d | cout = %b sum = %d | correct!! = %b", a, b, cout, sum, cor);
        #10 a = 5;
        b   = 1;
        sel = 0;
        #10 a = 5;
        b   = 1;
        sel = 1;
        #10 a = 0;
        b   = 0;
        sel = 0;
        #10 a = 0;
        b   = 0;
        sel = 1;
        #10 a = 2;
        b   = 2;
        sel = 0;
        #10 a = 2;
        b   = 2;
        sel = 1;
        #10 a = 1;
        b   = 5;
        sel = 0;
        #10 a = 1;
        b   = 5;
        sel = 1;
        #10 $finish;
    end

    AddSub4 AddSub4 (
        a,
        b,
        sel,
        cout,
        sum
    );
endmodule

邏輯設計實驗/二/2/test.vcd
$date
	Tue Mar 12 17:33:50 2024
$end
$version
	Icarus Verilog
$end
$timescale
	1ps
$end
$scope module TM_AddSub4 $end
$scope module AddSub4 $end
$var wire 4 ! a [3:0] $end
$var wire 4 " b [3:0] $end
$var wire 1 # sel $end
$var wire 4 $ sum [3:0] $end
$var wire 1 % cout $end
$upscope $end
$upscope $end
$enddefinitions $end
$comment Show the parameter values. $end
$dumpall
$end
#0
$dumpvars
x%
bx $
x#
bx "
bx !
$end
#10000
b110 $
0%
0#
b1 "
b101 !
#20000
b100 $
1%
1#
#30000
b0 $
0%
0#
b0 "
b0 !
#40000
1%
1#
#50000
b100 $
0%
0#
b10 "
b10 !
#60000
b0 $
1%
1#
#70000
b110 $
0%
0#
b101 "
b1 !
#80000
b1100 $
1#
