邏輯設計實驗/一/LAB 期末/vending_machine.v
module vending_machine (
    clk,
    reset,
    howManyTicket,
    origin,
    destination,
    money,
    costOfTicket,
    moneyToPay,
    totalMoney
);


    input clk;
    input reset;
    input [31:0] howManyTicket;
    input [31:0] origin;
    input [31:0] destination;
    input [31:0] money;
    output [31:0] costOfTicket;
    assign costOfTicket = tempprice;
    output [31:0] moneyToPay;
    assign moneyToPay = totalcost;
    output [31:0] totalMoney;
    assign totalMoney = tempmoney;

    reg [31:0] tempmoney;
    reg [31:0] totalcost;
    reg [31:0] state;
    reg [31:0] tempprice;
    reg [31:0] tickamount;
    reg [31:0] Tickets;
    reg [31:0] returnmoney;

    always @(negedge clk) begin
        if (reset) begin
            state <= 3;
            $display("取消");
        end
    end

    always @(posedge clk) begin
        case (state)
            0: begin
                tempmoney = 0;
                totalcost = 0;
                tempprice = 0;
                tickamount = 0;
                Tickets = 0;
                returnmoney = 0;
                tempprice = origin - destination;
                $display("起駛站S%d", origin);
                $display("終駛站S%d", destination);
                if (origin < destination) begin
                    tempprice = -tempprice;
                end
                tempprice = tempprice + 1;
                tempprice = tempprice * 5;
            end
            1: begin
                totalcost = tempprice * howManyTicket;
                $display("買%d張票", howManyTicket);
                $display("需要付%d元", totalcost);
                tickamount = howManyTicket;
            end
            2: begin
                tempmoney = tempmoney + money;
                $display("投%d元,總共投%d元", money, tempmoney);
            end
            3: begin
                if (tempmoney >= totalcost) begin
                    returnmoney = tempmoney - totalcost;
                    Tickets = tickamount;
                    $display("找%d元,車票%d張", returnmoney, Tickets);
                end else begin
                    returnmoney = tempmoney;
                    Tickets = 0;
                    $display("找%d元", returnmoney);
                end
            end
        endcase
    end



    always @(negedge clk) begin
        if (!reset) begin
            case (state)
                0: begin
                    state = 1;
                end
                1: begin
                    state = 2;
                end
                2: begin
                    if (tempmoney >= totalcost) begin
                        state = 3;
                    end else begin
                        $display("還需要%d元", totalcost - tempmoney);
                    end
                end
                3: begin
                    state = 0;
                end
                default: begin
                    state = 0;
                end
            endcase
        end
    end


endmodule

邏輯設計實驗/一/LAB 期末/stimulus.v
module stimulus;
    reg clk;
    always begin
        clk = 0;
        #5;
        clk = 1;
        #5;
    end


    vending_machine vending_machine (
        clk,
        reset,
        howManyTicket,
        origin,
        destination,
        money,
        costOfTicket,
        moneyToPay,
        totalMoney
    );
    reg reset;
    reg [31:0] howManyTicket, origin, destination, money;
    wire [31:0] costOfTicket, moneyToPay, totalMoney;
    integer i;
    initial begin
        $dumpfile("test.vcd");
        $dumpvars(2, vending_machine);
        reset = 1;
        #10 reset = 0;
        //loop begin
        origin = 5;
        destination = 3;
        #10 howManyTicket = 4;
        #10 money = 5;
        #10 money = 10;
        #10 money = 50;
        #10 money = 0;
        #10;
        //loop end
        //loop begin
        origin = 3;
        destination = 4;
        #10 howManyTicket = 2;
        #10 money = 10;
        #10 money = 0;
        reset = 1;
        #10;
        //loop end        
        /*
        for (i = 0; i < 10; i = i + 1) begin
            //loop begin
            origin = i + 1;
            destination = i + 4;
            #10 howManyTicket = 5 + i;
            #10 money = 10;
            #10 money = 1000 + i;
            #10 money = 0;
            #10;
            //loop end
        end
        */
        $finish;


    end



endmodule

邏輯設計實驗/一/LAB 期末/test.vcd
$date
	Thu Jan 04 09:31:56 2024
$end
$version
	Icarus Verilog
$end
$timescale
	1s
$end
$scope module stimulus $end
$scope module vending_machine $end
$var wire 1 ! clk $end
$var wire 32 " costOfTicket [31:0] $end
$var wire 32 # destination [31:0] $end
$var wire 32 $ howManyTicket [31:0] $end
$var wire 32 % money [31:0] $end
$var wire 32 & moneyToPay [31:0] $end
$var wire 32 ' origin [31:0] $end
$var wire 1 ( reset $end
$var wire 32 ) totalMoney [31:0] $end
$var reg 32 * Tickets [31:0] $end
$var reg 32 + returnmoney [31:0] $end
$var reg 32 , state [31:0] $end
$var reg 32 - tempmoney [31:0] $end
$var reg 32 . tempprice [31:0] $end
$var reg 32 / tickamount [31:0] $end
$var reg 32 0 totalcost [31:0] $end
$upscope $end
$upscope $end
$enddefinitions $end
$comment Show the parameter values. $end
$dumpall
$end
#0
$dumpvars
bx 0
bx /
bx .
bx -
b11 ,
bx +
bx *
bx )
1(
bx '
bx &
bx %
bx $
bx #
bx "
0!
$end
#5
b0 *
1!
#10
b0 ,
0!
b11 #
b101 '
0(
#15
b0 +
b0 /
b1111 "
b1111 .
b0 &
b0 0
b0 )
b0 -
1!
#20
b1 ,
0!
b100 $
#25
b100 /
b111100 &
b111100 0
1!
#30
b10 ,
0!
b101 %
#35
b101 )
b101 -
1!
#40
0!
b1010 %
#45
b1111 )
b1111 -
1!
#50
0!
b110010 %
#55
b1000001 )
b1000001 -
1!
#60
b11 ,
0!
b0 %
#65
b100 *
b101 +
1!
#70
b0 ,
0!
b100 #
b11 '
#75
b0 +
b0 *
b0 /
b1010 "
b1010 .
b0 &
b0 0
b0 )
b0 -
1!
#80
b1 ,
0!
b10 $
#85
b10 /
b10100 &
b10100 0
1!
#90
b10 ,
0!
b1010 %
#95
b1010 )
b1010 -
1!
#100
b11 ,
0!
1(
b0 %
#105
b1010 +
1!
