邏輯設計實驗/一/LAB3/Comparator.v
module Comparator (
    A,
    B,
    A_gt_b,
    A_eq_b,
    A_lt_b
);

    output A_gt_b, A_eq_b, A_lt_b;
    input [3:0] A, B;

    assign A_gt_b = A[3]&(!B[3]) | ((A[3]^~B[3]) & A[2]&&(!B[2])) | ((A[3]^~B[3]) &(A[2]^~B[2]) & A[1]&(!B[1])) | ((A[3]^~B[3]) &(A[2]^~B[2]) &(A[1]^~B[1])& A[0]&(!B[0]));
    assign A_eq_b = (A[3] ^~ B[3]) & (A[2] ^~ B[2]) & (A[1] ^~ B[1]) & (A[0] ^~ B[0]);
    assign A_lt_b = !(A_gt_b | A_eq_b);


endmodule

邏輯設計實驗/一/LAB3/stimulus.v
module stimulus;

    reg [7:0] count;

    wire A_gt_b, A_eq_b, A_lt_b;
    wire [3:0] A;
    wire [3:0] B;
    assign A = count[7:4];
    assign B = count[3:0];

    Comparator comparator (
        A,
        B,
        A_gt_b,
        A_eq_b,
        A_lt_b
    );


    integer i;
    initial begin
        $dumpfile("test.vcd");
        $dumpvars(0, comparator);
        $monitor(" a = %d, b = %d, %b%b%b", A, B, A_gt_b, A_eq_b, A_lt_b);
        for (i = 0; i < 256; i = i + 1) begin
            count <= i;
            #10;
        end
        $finish;

    end



endmodule

邏輯設計實驗/一/LAB3/test.vcd
$date
	Sat Oct 07 15:38:23 2023
$end
$version
	Icarus Verilog
$end
$timescale
	1s
$end
$scope module stimulus $end
$scope module comparator $end
$var wire 4 ! A [3:0] $end
$var wire 1 " A_eq_b $end
$var wire 1 # A_gt_b $end
$var wire 4 $ B [3:0] $end
$var wire 1 % A_lt_b $end
$upscope $end
$upscope $end
$enddefinitions $end
$comment Show the parameter values. $end
$dumpall
$end
#0
$dumpvars
0%
b0 $
0#
1"
b0 !
$end
#10
1%
0"
b1 $
#20
1%
0"
b10 $
#30
b11 $
#40
1%
0"
b100 $
#50
b101 $
#60
b110 $
#70
b111 $
#80
b1000 $
#90
b1001 $
#100
b1010 $
#110
b1011 $
#120
b1100 $
#130
b1101 $
#140
b1110 $
#150
b1111 $
#160
0%
1#
b1 !
b0 $
#170
0#
1"
b1 $
#180
1%
0#
0"
b10 $
#190
b11 $
#200
1%
0#
b100 $
#210
b101 $
#220
b110 $
#230
b111 $
#240
b1000 $
#250
b1001 $
#260
b1010 $
#270
b1011 $
#280
b1100 $
#290
b1101 $
#300
b1110 $
#310
b1111 $
#320
0%
1#
b10 !
b0 $
#330
b1 $
#340
0#
1"
b10 $
#350
1%
0"
b11 $
#360
0#
1%
0"
b100 $
#370
b101 $
#380
b110 $
#390
b111 $
#400
b1000 $
#410
b1001 $
#420
b1010 $
#430
b1011 $
#440
b1100 $
#450
b1101 $
#460
b1110 $
#470
b1111 $
#480
0%
1#
b11 !
b0 $
#490
b1 $
#500
0%
1#
b10 $
#510
0#
1"
b11 $
#520
1%
0#
0"
b100 $
#530
b101 $
#540
b110 $
#550
b111 $
#560
b1000 $
#570
b1001 $
#580
b1010 $
#590
b1011 $
#600
b1100 $
#610
b1101 $
#620
b1110 $
#630
b1111 $
#640
0%
1#
b100 !
b0 $
#650
b1 $
#660
b10 $
#670
b11 $
#680
0#
1"
b100 $
#690
1%
0"
b101 $
#700
1%
0"
b110 $
#710
b111 $
#720
0#
1%
0"
b1000 $
#730
b1001 $
#740
b1010 $
#750
b1011 $
#760
b1100 $
#770
b1101 $
#780
b1110 $
#790
b1111 $
#800
0%
1#
b101 !
b0 $
#810
b1 $
#820
b10 $
#830
b11 $
#840
0%
1#
b100 $
#850
0#
1"
b101 $
#860
1%
0#
0"
b110 $
#870
b111 $
#880
1%
0#
b1000 $
#890
b1001 $
#900
b1010 $
#910
b1011 $
#920
b1100 $
#930
b1101 $
#940
b1110 $
#950
b1111 $
#960
0%
1#
b110 !
b0 $
#970
b1 $
#980
b10 $
#990
b11 $
#1000
0%
1#
b100 $
#1010
b101 $
#1020
0#
1"
b110 $
#1030
1%
0"
b111 $
#1040
0#
1%
0"
b1000 $
#1050
b1001 $
#1060
b1010 $
#1070
b1011 $
#1080
b1100 $
#1090
b1101 $
#1100
b1110 $
#1110
b1111 $
#1120
0%
1#
b111 !
b0 $
#1130
b1 $
#1140
b10 $
#1150
b11 $
#1160
0%
1#
b100 $
#1170
b101 $
#1180
0%
1#
b110 $
#1190
0#
1"
b111 $
#1200
1%
0#
0"
b1000 $
#1210
b1001 $
#1220
b1010 $
#1230
b1011 $
#1240
b1100 $
#1250
b1101 $
#1260
b1110 $
#1270
b1111 $
#1280
0%
1#
b1000 !
b0 $
#1290
b1 $
#1300
b10 $
#1310
b11 $
#1320
b100 $
#1330
b101 $
#1340
b110 $
#1350
b111 $
#1360
0#
1"
b1000 $
#1370
1%
0"
b1001 $
#1380
1%
0"
b1010 $
#1390
b1011 $
#1400
1%
0"
b1100 $
#1410
b1101 $
#1420
b1110 $
#1430
b1111 $
#1440
0%
1#
b1001 !
b0 $
#1450
b1 $
#1460
b10 $
#1470
b11 $
#1480
b100 $
#1490
b101 $
#1500
b110 $
#1510
b111 $
#1520
0%
1#
b1000 $
#1530
0#
1"
b1001 $
#1540
1%
0#
0"
b1010 $
#1550
b1011 $
#1560
1%
0#
b1100 $
#1570
b1101 $
#1580
b1110 $
#1590
b1111 $
#1600
0%
1#
b1010 !
b0 $
#1610
b1 $
#1620
b10 $
#1630
b11 $
#1640
b100 $
#1650
b101 $
#1660
b110 $
#1670
b111 $
#1680
0%
1#
b1000 $
#1690
b1001 $
#1700
0#
1"
b1010 $
#1710
1%
0"
b1011 $
#1720
0#
1%
0"
b1100 $
#1730
b1101 $
#1740
b1110 $
#1750
b1111 $
#1760
0%
1#
b1011 !
b0 $
#1770
b1 $
#1780
b10 $
#1790
b11 $
#1800
b100 $
#1810
b101 $
#1820
b110 $
#1830
b111 $
#1840
0%
1#
b1000 $
#1850
b1001 $
#1860
0%
1#
b1010 $
#1870
0#
1"
b1011 $
#1880
1%
0#
0"
b1100 $
#1890
b1101 $
#1900
b1110 $
#1910
b1111 $
#1920
0%
1#
b1100 !
b0 $
#1930
b1 $
#1940
b10 $
#1950
b11 $
#1960
b100 $
#1970
b101 $
#1980
b110 $
#1990
b111 $
#2000
0%
1#
b1000 $
#2010
b1001 $
#2020
b1010 $
#2030
b1011 $
#2040
0#
1"
b1100 $
#2050
1%
0"
b1101 $
#2060
1%
0"
b1110 $
#2070
b1111 $
#2080
0%
1#
b1101 !
b0 $
#2090
b1 $
#2100
b10 $
#2110
b11 $
#2120
b100 $
#2130
b101 $
#2140
b110 $
#2150
b111 $
#2160
0%
1#
b1000 $
#2170
b1001 $
#2180
b1010 $
#2190
b1011 $
#2200
0%
1#
b1100 $
#2210
0#
1"
b1101 $
#2220
1%
0#
0"
b1110 $
#2230
b1111 $
#2240
0%
1#
b1110 !
b0 $
#2250
b1 $
#2260
b10 $
#2270
b11 $
#2280
b100 $
#2290
b101 $
#2300
b110 $
#2310
b111 $
#2320
0%
1#
b1000 $
#2330
b1001 $
#2340
b1010 $
#2350
b1011 $
#2360
0%
1#
b1100 $
#2370
b1101 $
#2380
0#
1"
b1110 $
#2390
1%
0"
b1111 $
#2400
0%
1#
b1111 !
b0 $
#2410
b1 $
#2420
b10 $
#2430
b11 $
#2440
b100 $
#2450
b101 $
#2460
b110 $
#2470
b111 $
#2480
0%
1#
b1000 $
#2490
b1001 $
#2500
b1010 $
#2510
b1011 $
#2520
0%
1#
b1100 $
#2530
b1101 $
#2540
0%
1#
b1110 $
#2550
0#
1"
b1111 $
