邏輯設計實驗/一/LAB4/substractor.v
module substractor (
    x,
    y,
    z,
    b,
    d
);

    output b, d;
    input x, y, z;

    assign d = (!x) & (!y) & z | (!x) & y & (!z) | x & (!y) & (!z) | x & y & z;
    assign b = (!x) & y | (!x) & z | y & z;

endmodule

module substractor_4 (
    x,
    y,
    z,
    b,
    d
);

    input [3:0] x, y;
    input z;
    output [3:0] b, d;
    wire [3:0] bo;
    assign b = bo;

    substractor sub_0 (
        x[0],
        y[0],
        z,
        bo[0],
        d[0]
    );
    substractor sub_1 (
        x[1],
        y[1],
        bo[0],
        bo[1],
        d[1]
    );
    substractor sub_2 (
        x[2],
        y[2],
        bo[1],
        bo[2],
        d[2]
    );
    substractor sub_3 (
        x[3],
        y[3],
        bo[2],
        bo[3],
        d[3]
    );


endmodule

邏輯設計實驗/一/LAB4/stimulus.v
module stimulus;

    reg [8:0] count;

    wire [3:0] x;
    wire [3:0] y;
    wire z;
    wire [3:0] b, d;
    assign z = count[8];
    assign x = count[7:4];
    assign y = count[3:0];

    substractor_4 substractor (
        x,
        y,
        z,
        b,
        d
    );


    integer i;
    initial begin
        $dumpfile("test.vcd");
        $dumpvars(0, substractor);
        for (i = 0; i < 512; i = i + 1) begin
            count <= i;
            #10;
        end
        $finish;

    end



endmodule

邏輯設計實驗/一/LAB4/test.vcd
$date
	Tue Oct 17 02:51:03 2023
$end
$version
	Icarus Verilog
$end
$timescale
	1s
$end
$scope module stimulus $end
$scope module substractor $end
$var wire 4 ! b [3:0] $end
$var wire 4 " x [3:0] $end
$var wire 4 # y [3:0] $end
$var wire 1 $ z $end
$var wire 4 % d [3:0] $end
$var wire 4 & bo [3:0] $end
$scope module sub_0 $end
$var wire 1 ' b $end
$var wire 1 ( d $end
$var wire 1 ) x $end
$var wire 1 * y $end
$var wire 1 $ z $end
$upscope $end
$scope module sub_1 $end
$var wire 1 + b $end
$var wire 1 , d $end
$var wire 1 - x $end
$var wire 1 . y $end
$var wire 1 / z $end
$upscope $end
$scope module sub_2 $end
$var wire 1 0 b $end
$var wire 1 1 d $end
$var wire 1 2 x $end
$var wire 1 3 y $end
$var wire 1 4 z $end
$upscope $end
$scope module sub_3 $end
$var wire 1 5 b $end
$var wire 1 6 d $end
$var wire 1 7 x $end
$var wire 1 8 y $end
$var wire 1 9 z $end
$upscope $end
$upscope $end
$upscope $end
$enddefinitions $end
$comment Show the parameter values. $end
$dumpall
$end
#0
$dumpvars
09
08
07
06
05
04
03
02
01
00
0/
0.
0-
0,
0+
0*
0)
0(
0'
b0 &
b0 %
0$
b0 #
b0 "
b0 !
$end
#10
16
15
11
19
10
1,
14
1+
b1111 %
1(
1/
b1111 !
b1111 &
1'
1*
b1 #
#20
0(
b1110 %
1,
0/
b1110 !
b1110 &
0'
0*
1.
b10 #
#30
0,
b1101 %
1(
1/
b1111 !
b1111 &
1'
1*
b11 #
#40
04
0+
0(
0,
b1100 %
11
0/
b1100 !
b1100 &
0'
0*
0.
13
b100 #
#50
01
1,
14
1+
b1011 %
1(
1/
b1111 !
b1111 &
1'
1*
b101 #
#60
0(
b1010 %
1,
0/
b1110 !
b1110 &
0'
0*
1.
b110 #
#70
0,
b1001 %
1(
1/
b1111 !
b1111 &
1'
1*
b111 #
#80
09
00
04
0+
0(
0,
01
b1000 %
16
0/
b1000 !
b1000 &
0'
0*
0.
03
18
b1000 #
#90
06
11
19
10
1,
14
1+
b111 %
1(
1/
b1111 !
b1111 &
1'
1*
b1001 #
#100
0(
b110 %
1,
0/
b1110 !
b1110 &
0'
0*
1.
b1010 #
#110
0,
b101 %
1(
1/
b1111 !
b1111 &
1'
1*
b1011 #
#120
04
0+
0(
0,
b100 %
11
0/
b1100 !
b1100 &
0'
0*
0.
13
b1100 #
#130
01
1,
14
1+
b11 %
1(
1/
b1111 !
b1111 &
1'
1*
b1101 #
#140
0(
b10 %
1,
0/
b1110 !
b1110 &
0'
0*
1.
b1110 #
#150
0,
b1 %
1(
1/
b1111 !
b1111 &
1'
1*
b1111 #
#160
05
09
00
04
0+
0,
01
b1 %
06
0/
b0 !
b0 &
0'
1)
0*
0.
03
08
b1 "
b0 #
#170
b0 %
0(
1*
b1 #
#180
16
15
11
19
10
1,
b1111 %
1(
14
b1110 !
b1110 &
1+
0*
1.
b10 #
#190
b1110 %
0(
1*
b11 #
#200
0,
11
b1101 %
1(
04
b1100 !
b1100 &
0+
0*
0.
13
b100 #
#210
b1100 %
0(
1*
b101 #
#220
01
1,
b1011 %
1(
14
b1110 !
b1110 &
1+
0*
1.
b110 #
#230
b1010 %
0(
1*
b111 #
#240
09
00
0,
01
16
b1001 %
1(
04
b1000 !
b1000 &
0+
0*
0.
03
18
b1000 #
#250
b1000 %
0(
1*
b1001 #
#260
06
11
19
10
1,
b111 %
1(
14
b1110 !
b1110 &
1+
0*
1.
b1010 #
#270
b110 %
0(
1*
b1011 #
#280
0,
11
b101 %
1(
04
b1100 !
b1100 &
0+
0*
0.
13
b1100 #
#290
b100 %
0(
1*
b1101 #
#300
01
1,
b11 %
1(
14
b1110 !
b1110 &
1+
0*
1.
b1110 #
#310
b10 %
0(
1*
b1111 #
#320
05
09
00
01
b10 %
06
04
b0 !
b0 &
0+
0)
1-
0*
0.
03
08
b10 "
b0 #
#330
0,
b1 %
1(
1/
b1 !
b1 &
1'
1*
b1 #
#340
06
05
01
09
00
0(
0/
0'
b0 %
0,
04
b0 !
b0 &
0+
0*
1.
b10 #
#350
16
15
11
19
10
14
1,
1+
b1111 %
1(
1/
b1111 !
b1111 &
1'
1*
b11 #
#360
0(
11
0/
0'
b1110 %
1,
04
b1100 !
b1100 &
0+
0*
0.
13
b100 #
#370
0,
b1101 %
1(
1/
b1101 !
b1101 &
1'
1*
b101 #
#380
11
0(
0/
0'
b1100 %
0,
04
b1100 !
b1100 &
0+
0*
1.
b110 #
#390
01
14
1,
1+
b1011 %
1(
1/
b1111 !
b1111 &
1'
1*
b111 #
#400
09
00
0(
01
16
0/
0'
b1010 %
1,
04
b1000 !
b1000 &
0+
0*
0.
03
18
b1000 #
#410
0,
b1001 %
1(
1/
b1001 !
b1001 &
1'
1*
b1001 #
#420
16
01
09
00
0(
0/
0'
b1000 %
0,
04
b1000 !
b1000 &
0+
0*
1.
b1010 #
#430
06
11
19
10
14
1,
1+
b111 %
1(
1/
b1111 !
b1111 &
1'
1*
b1011 #
#440
0(
11
0/
0'
b110 %
1,
04
b1100 !
b1100 &
0+
0*
0.
13
b1100 #
#450
0,
b101 %
1(
1/
b1101 !
b1101 &
1'
1*
b1101 #
#460
11
0(
0/
0'
b100 %
0,
04
b1100 !
b1100 &
0+
0*
1.
b1110 #
#470
01
14
1,
1+
b11 %
1(
1/
b1111 !
b1111 &
1'
1*
b1111 #
#480
05
09
00
01
06
0/
0'
b11 %
1,
04
b0 !
b0 &
0+
1)
0*
0.
03
08
b11 "
b0 #
#490
b10 %
0(
1*
b1 #
#500
1(
b1 %
0,
0*
1.
b10 #
#510
b0 %
0(
1*
b11 #
#520
16
15
11
1(
b1111 %
1,
19
b1100 !
b1100 &
10
0*
0.
13
b100 #
#530
b1110 %
0(
1*
b101 #
#540
1(
b1101 %
0,
0*
1.
b110 #
#550
b1100 %
0(
1*
b111 #
#560
01
16
1(
b1011 %
1,
09
b1000 !
b1000 &
00
0*
0.
03
18
b1000 #
#570
b1010 %
0(
1*
b1001 #
#580
1(
b1001 %
0,
0*
1.
b1010 #
#590
b1000 %
0(
1*
b1011 #
#600
06
11
1(
b111 %
1,
19
b1100 !
b1100 &
10
0*
0.
13
b1100 #
#610
b110 %
0(
1*
b1101 #
#620
1(
b101 %
0,
0*
1.
b1110 #
#630
b100 %
0(
1*
b1111 #
#640
05
b100 %
06
09
b0 !
b0 &
00
0)
0-
12
0*
0.
03
08
b100 "
b0 #
#650
01
1,
14
1+
b11 %
1(
1/
b11 !
b11 &
1'
1*
b1 #
#660
0(
b10 %
1,
0/
b10 !
b10 &
0'
0*
1.
b10 #
#670
0,
b1 %
1(
1/
b11 !
b11 &
1'
1*
b11 #
#680
04
0+
06
05
0(
0,
0/
0'
b0 %
01
09
b0 !
b0 &
00
0*
0.
13
b100 #
#690
16
15
19
11
10
1,
14
1+
b1111 %
1(
1/
b1111 !
b1111 &
1'
1*
b101 #
#700
0(
b1110 %
1,
0/
b1110 !
b1110 &
0'
0*
1.
b110 #
#710
0,
b1101 %
1(
1/
b1111 !
b1111 &
1'
1*
b111 #
#720
04
0+
0(
0,
16
0/
0'
b1100 %
11
09
b1000 !
b1000 &
00
0*
0.
03
18
b1000 #
#730
01
1,
14
1+
b1011 %
1(
1/
b1011 !
b1011 &
1'
1*
b1001 #
#740
0(
b1010 %
1,
0/
b1010 !
b1010 &
0'
0*
1.
b1010 #
#750
0,
b1001 %
1(
1/
b1011 !
b1011 &
1'
1*
b1011 #
#760
04
0+
16
0(
0,
0/
0'
b1000 %
01
09
b1000 !
b1000 &
00
0*
0.
13
b1100 #
#770
06
19
11
10
1,
14
1+
b111 %
1(
1/
b1111 !
b1111 &
1'
1*
b1101 #
#780
0(
b110 %
1,
0/
b1110 !
b1110 &
0'
0*
1.
b1110 #
#790
0,
b101 %
1(
1/
b1111 !
b1111 &
1'
1*
b1111 #
#800
04
0+
05
0,
06
0/
0'
b101 %
11
09
b0 !
b0 &
00
1)
0*
0.
03
08
b101 "
b0 #
#810
b100 %
0(
1*
b1 #
#820
01
1,
b11 %
1(
14
b10 !
b10 &
1+
0*
1.
b10 #
#830
b10 %
0(
1*
b11 #
#840
06
05
0,
1(
04
0+
b1 %
01
09
b0 !
b0 &
00
0*
0.
13
b100 #
#850
b0 %
0(
1*
b101 #
#860
16
15
19
11
10
1,
b1111 %
1(
14
b1110 !
b1110 &
1+
0*
1.
b110 #
#870
b1110 %
0(
1*
b111 #
#880
0,
16
1(
04
0+
b1101 %
11
09
b1000 !
b1000 &
00
0*
0.
03
18
b1000 #
#890
b1100 %
0(
1*
b1001 #
#900
01
1,
b1011 %
1(
14
b1010 !
b1010 &
1+
0*
1.
b1010 #
#910
b1010 %
0(
1*
b1011 #
#920
16
0,
1(
04
0+
b1001 %
01
09
b1000 !
b1000 &
00
0*
0.
13
b1100 #
#930
b1000 %
0(
1*
b1101 #
#940
06
19
11
10
1,
b111 %
1(
14
b1110 !
b1110 &
1+
0*
1.
b1110 #
#950
b110 %
0(
1*
b1111 #
#960
05
06
04
0+
b110 %
11
09
b0 !
b0 &
00
0)
1-
0*
0.
03
08
b110 "
b0 #
#970
0,
b101 %
1(
1/
b1 !
b1 &
1'
1*
b1 #
#980
11
0(
0/
0'
b100 %
0,
04
b0 !
b0 &
0+
0*
1.
b10 #
#990
01
14
1,
1+
b11 %
1(
1/
b11 !
b11 &
1'
1*
b11 #
#1000
06
05
0(
0/
0'
1,
04
b10 %
01
09
0+
b0 !
b0 &
00
0*
0.
13
b100 #
#1010
0,
b1 %
1(
1/
b1 !
b1 &
1'
1*
b101 #
#1020
06
05
09
0(
01
00
0/
0'
b0 %
0,
04
b0 !
b0 &
0+
0*
1.
b110 #
#1030
16
15
19
11
10
14
1,
1+
b1111 %
1(
1/
b1111 !
b1111 &
1'
1*
b111 #
#1040
0(
16
0/
0'
1,
04
b1110 %
11
09
0+
b1000 !
b1000 &
00
0*
0.
03
18
b1000 #
#1050
0,
b1101 %
1(
1/
b1001 !
b1001 &
1'
1*
b1001 #
#1060
11
0(
0/
0'
b1100 %
0,
04
b1000 !
b1000 &
0+
0*
1.
b1010 #
#1070
01
14
1,
1+
b1011 %
1(
1/
b1011 !
b1011 &
1'
1*
b1011 #
#1080
16
0(
0/
0'
1,
04
b1010 %
01
09
0+
b1000 !
b1000 &
00
0*
0.
13
b1100 #
#1090
0,
b1001 %
1(
1/
b1001 !
b1001 &
1'
1*
b1101 #
#1100
16
09
0(
01
00
0/
0'
b1000 %
0,
04
b1000 !
b1000 &
0+
0*
1.
b1110 #
#1110
06
19
11
10
14
1,
1+
b111 %
1(
1/
b1111 !
b1111 &
1'
1*
b1111 #
#1120
05
06
0/
0'
1,
04
b111 %
11
09
0+
b0 !
b0 &
00
1)
0*
0.
03
08
b111 "
b0 #
#1130
b110 %
0(
1*
b1 #
#1140
1(
b101 %
0,
0*
1.
b10 #
#1150
b100 %
0(
1*
b11 #
#1160
1(
1,
b11 %
01
0*
0.
13
b100 #
#1170
b10 %
0(
1*
b101 #
#1180
1(
b1 %
0,
0*
1.
b110 #
#1190
b0 %
0(
1*
b111 #
#1200
16
1(
1,
b1111 %
11
b1000 !
b1000 &
15
0*
0.
03
18
b1000 #
#1210
b1110 %
0(
1*
b1001 #
#1220
1(
b1101 %
0,
0*
1.
b1010 #
#1230
b1100 %
0(
1*
b1011 #
#1240
1(
1,
b1011 %
01
0*
0.
13
b1100 #
#1250
b1010 %
0(
1*
b1101 #
#1260
1(
b1001 %
0,
0*
1.
b1110 #
#1270
b1000 %
0(
1*
b1111 #
#1280
b0 !
b0 &
05
0)
0-
02
17
0*
0.
03
08
b1000 "
b0 #
#1290
06
11
19
10
1,
14
1+
b111 %
1(
1/
b111 !
b111 &
1'
1*
b1 #
#1300
0(
b110 %
1,
0/
b110 !
b110 &
0'
0*
1.
b10 #
#1310
0,
b101 %
1(
1/
b111 !
b111 &
1'
1*
b11 #
#1320
04
0+
0(
0,
b100 %
11
0/
b100 !
b100 &
0'
0*
0.
13
b100 #
#1330
01
1,
14
1+
b11 %
1(
1/
b111 !
b111 &
1'
1*
b101 #
#1340
0(
b10 %
1,
0/
b110 !
b110 &
0'
0*
1.
b110 #
#1350
0,
b1 %
1(
1/
b111 !
b111 &
1'
1*
b111 #
#1360
09
00
04
0+
0(
0,
01
0/
0'
b0 %
06
b0 !
b0 &
05
0*
0.
03
18
b1000 #
#1370
16
15
11
19
10
1,
14
1+
b1111 %
1(
1/
b1111 !
b1111 &
1'
1*
b1001 #
#1380
0(
b1110 %
1,
0/
b1110 !
b1110 &
0'
0*
1.
b1010 #
#1390
0,
b1101 %
1(
1/
b1111 !
b1111 &
1'
1*
b1011 #
#1400
04
0+
0(
0,
b1100 %
11
0/
b1100 !
b1100 &
0'
0*
0.
13
b1100 #
#1410
01
1,
14
1+
b1011 %
1(
1/
b1111 !
b1111 &
1'
1*
b1101 #
#1420
0(
b1010 %
1,
0/
b1110 !
b1110 &
0'
0*
1.
b1110 #
#1430
0,
b1001 %
1(
1/
b1111 !
b1111 &
1'
1*
b1111 #
#1440
09
00
04
0+
0,
01
0/
0'
b1001 %
16
b0 !
b0 &
05
1)
0*
0.
03
08
b1001 "
b0 #
#1450
b1000 %
0(
1*
b1 #
#1460
06
11
19
10
1,
b111 %
1(
14
b110 !
b110 &
1+
0*
1.
b10 #
#1470
b110 %
0(
1*
b11 #
#1480
0,
11
b101 %
1(
04
b100 !
b100 &
0+
0*
0.
13
b100 #
#1490
b100 %
0(
1*
b101 #
#1500
01
1,
b11 %
1(
14
b110 !
b110 &
1+
0*
1.
b110 #
#1510
b10 %
0(
1*
b111 #
#1520
09
00
0,
01
1(
04
0+
b1 %
06
b0 !
b0 &
05
0*
0.
03
18
b1000 #
#1530
b0 %
0(
1*
b1001 #
#1540
16
15
11
19
10
1,
b1111 %
1(
14
b1110 !
b1110 &
1+
0*
1.
b1010 #
#1550
b1110 %
0(
1*
b1011 #
#1560
0,
11
b1101 %
1(
04
b1100 !
b1100 &
0+
0*
0.
13
b1100 #
#1570
b1100 %
0(
1*
b1101 #
#1580
01
1,
b1011 %
1(
14
b1110 !
b1110 &
1+
0*
1.
b1110 #
#1590
b1010 %
0(
1*
b1111 #
#1600
09
00
01
04
0+
b1010 %
16
b0 !
b0 &
05
0)
1-
0*
0.
03
08
b1010 "
b0 #
#1610
0,
b1001 %
1(
1/
b1 !
b1 &
1'
1*
b1 #
#1620
16
01
09
00
0(
0/
0'
b1000 %
0,
04
b0 !
b0 &
0+
0*
1.
b10 #
#1630
06
11
19
10
14
1,
1+
b111 %
1(
1/
b111 !
b111 &
1'
1*
b11 #
#1640
0(
11
0/
0'
b110 %
1,
04
b100 !
b100 &
0+
0*
0.
13
b100 #
#1650
0,
b101 %
1(
1/
b101 !
b101 &
1'
1*
b101 #
#1660
11
0(
0/
0'
b100 %
0,
04
b100 !
b100 &
0+
0*
1.
b110 #
#1670
01
14
1,
1+
b11 %
1(
1/
b111 !
b111 &
1'
1*
b111 #
#1680
09
00
0(
01
0/
0'
1,
04
b10 %
06
0+
b0 !
b0 &
05
0*
0.
03
18
b1000 #
#1690
0,
b1 %
1(
1/
b1 !
b1 &
1'
1*
b1001 #
#1700
06
05
01
09
00
0(
0/
0'
b0 %
0,
04
b0 !
b0 &
0+
0*
1.
b1010 #
#1710
16
15
11
19
10
14
1,
1+
b1111 %
1(
1/
b1111 !
b1111 &
1'
1*
b1011 #
#1720
0(
11
0/
0'
b1110 %
1,
04
b1100 !
b1100 &
0+
0*
0.
13
b1100 #
#1730
0,
b1101 %
1(
1/
b1101 !
b1101 &
1'
1*
b1101 #
#1740
11
0(
0/
0'
b1100 %
0,
04
b1100 !
b1100 &
0+
0*
1.
b1110 #
#1750
01
14
1,
1+
b1011 %
1(
1/
b1111 !
b1111 &
1'
1*
b1111 #
#1760
09
00
01
0/
0'
1,
04
b1011 %
16
0+
b0 !
b0 &
05
1)
0*
0.
03
08
b1011 "
b0 #
#1770
b1010 %
0(
1*
b1 #
#1780
1(
b1001 %
0,
0*
1.
b10 #
#1790
b1000 %
0(
1*
b11 #
#1800
06
11
1(
b111 %
1,
19
b100 !
b100 &
10
0*
0.
13
b100 #
#1810
b110 %
0(
1*
b101 #
#1820
1(
b101 %
0,
0*
1.
b110 #
#1830
b100 %
0(
1*
b111 #
#1840
01
1(
1,
09
00
b11 %
06
b0 !
b0 &
05
0*
0.
03
18
b1000 #
#1850
b10 %
0(
1*
b1001 #
#1860
1(
b1 %
0,
0*
1.
b1010 #
#1870
b0 %
0(
1*
b1011 #
#1880
16
15
11
1(
b1111 %
1,
19
b1100 !
b1100 &
10
0*
0.
13
b1100 #
#1890
b1110 %
0(
1*
b1101 #
#1900
1(
b1101 %
0,
0*
1.
b1110 #
#1910
b1100 %
0(
1*
b1111 #
#1920
09
00
b1100 %
16
b0 !
b0 &
05
0)
0-
12
0*
0.
03
08
b1100 "
b0 #
#1930
01
1,
14
1+
b1011 %
1(
1/
b11 !
b11 &
1'
1*
b1 #
#1940
0(
b1010 %
1,
0/
b10 !
b10 &
0'
0*
1.
b10 #
#1950
0,
b1001 %
1(
1/
b11 !
b11 &
1'
1*
b11 #
#1960
04
0+
16
0(
0,
0/
0'
b1000 %
01
09
b0 !
b0 &
00
0*
0.
13
b100 #
#1970
06
19
11
10
1,
14
1+
b111 %
1(
1/
b111 !
b111 &
1'
1*
b101 #
#1980
0(
b110 %
1,
0/
b110 !
b110 &
0'
0*
1.
b110 #
#1990
0,
b101 %
1(
1/
b111 !
b111 &
1'
1*
b111 #
#2000
04
0+
0(
0,
0/
0'
11
09
b100 %
06
00
b0 !
b0 &
05
0*
0.
03
18
b1000 #
#2010
01
1,
14
1+
b11 %
1(
1/
b11 !
b11 &
1'
1*
b1001 #
#2020
0(
b10 %
1,
0/
b10 !
b10 &
0'
0*
1.
b1010 #
#2030
0,
b1 %
1(
1/
b11 !
b11 &
1'
1*
b1011 #
#2040
04
0+
0(
0,
06
05
0/
0'
b0 %
01
09
b0 !
b0 &
00
0*
0.
13
b1100 #
#2050
16
15
19
11
10
1,
14
1+
b1111 %
1(
1/
b1111 !
b1111 &
1'
1*
b1101 #
#2060
0(
b1110 %
1,
0/
b1110 !
b1110 &
0'
0*
1.
b1110 #
#2070
0,
b1101 %
1(
1/
b1111 !
b1111 &
1'
1*
b1111 #
#2080
04
0+
0,
0/
0'
11
09
b1101 %
16
00
b0 !
b0 &
05
1)
0*
0.
03
08
b1101 "
b0 #
#2090
b1100 %
0(
1*
b1 #
#2100
01
1,
b1011 %
1(
14
b10 !
b10 &
1+
0*
1.
b10 #
#2110
b1010 %
0(
1*
b11 #
#2120
16
0,
1(
04
0+
b1001 %
01
09
b0 !
b0 &
00
0*
0.
13
b100 #
#2130
b1000 %
0(
1*
b101 #
#2140
06
19
11
10
1,
b111 %
1(
14
b110 !
b110 &
1+
0*
1.
b110 #
#2150
b110 %
0(
1*
b111 #
#2160
0,
1(
04
0+
11
09
b101 %
06
00
b0 !
b0 &
05
0*
0.
03
18
b1000 #
#2170
b100 %
0(
1*
b1001 #
#2180
01
1,
b11 %
1(
14
b10 !
b10 &
1+
0*
1.
b1010 #
#2190
b10 %
0(
1*
b1011 #
#2200
0,
06
05
1(
04
0+
b1 %
01
09
b0 !
b0 &
00
0*
0.
13
b1100 #
#2210
b0 %
0(
1*
b1101 #
#2220
16
15
19
11
10
1,
b1111 %
1(
14
b1110 !
b1110 &
1+
0*
1.
b1110 #
#2230
b1110 %
0(
1*
b1111 #
#2240
04
0+
11
09
b1110 %
16
00
b0 !
b0 &
05
0)
1-
0*
0.
03
08
b1110 "
b0 #
#2250
0,
b1101 %
1(
1/
b1 !
b1 &
1'
1*
b1 #
#2260
11
0(
0/
0'
b1100 %
0,
04
b0 !
b0 &
0+
0*
1.
b10 #
#2270
01
14
1,
1+
b1011 %
1(
1/
b11 !
b11 &
1'
1*
b11 #
#2280
16
0(
0/
0'
1,
04
b1010 %
01
09
0+
b0 !
b0 &
00
0*
0.
13
b100 #
#2290
0,
b1001 %
1(
1/
b1 !
b1 &
1'
1*
b101 #
#2300
16
09
0(
01
00
0/
0'
b1000 %
0,
04
b0 !
b0 &
0+
0*
1.
b110 #
#2310
06
19
11
10
14
1,
1+
b111 %
1(
1/
b111 !
b111 &
1'
1*
b111 #
#2320
0(
0/
0'
1,
04
11
09
b110 %
06
0+
00
b0 !
b0 &
05
0*
0.
03
18
b1000 #
#2330
0,
b101 %
1(
1/
b1 !
b1 &
1'
1*
b1001 #
#2340
11
0(
0/
0'
b100 %
0,
04
b0 !
b0 &
0+
0*
1.
b1010 #
#2350
01
14
1,
1+
b11 %
1(
1/
b11 !
b11 &
1'
1*
b1011 #
#2360
0(
06
05
0/
0'
1,
04
b10 %
01
09
0+
b0 !
b0 &
00
0*
0.
13
b1100 #
#2370
0,
b1 %
1(
1/
b1 !
b1 &
1'
1*
b1101 #
#2380
06
05
09
0(
01
00
0/
0'
b0 %
0,
04
b0 !
b0 &
0+
0*
1.
b1110 #
#2390
16
15
19
11
10
14
1,
1+
b1111 %
1(
1/
b1111 !
b1111 &
1'
1*
b1111 #
#2400
0/
0'
1,
04
11
09
b1111 %
16
0+
00
b0 !
b0 &
05
1)
0*
0.
03
08
b1111 "
b0 #
#2410
b1110 %
0(
1*
b1 #
#2420
1(
b1101 %
0,
0*
1.
b10 #
#2430
b1100 %
0(
1*
b11 #
#2440
1(
1,
b1011 %
01
0*
0.
13
b100 #
#2450
b1010 %
0(
1*
b101 #
#2460
1(
b1001 %
0,
0*
1.
b110 #
#2470
b1000 %
0(
1*
b111 #
#2480
1(
1,
11
b111 %
06
0*
0.
03
18
b1000 #
#2490
b110 %
0(
1*
b1001 #
#2500
1(
b101 %
0,
0*
1.
b1010 #
#2510
b100 %
0(
1*
b1011 #
#2520
1(
1,
b11 %
01
0*
0.
13
b1100 #
#2530
b10 %
0(
1*
b1101 #
#2540
1(
b1 %
0,
0*
1.
b1110 #
#2550
b0 %
0(
1*
b1111 #
#2560
16
15
11
19
10
1,
14
1+
1/
b1111 !
b1111 &
1'
b1111 %
1(
0)
0-
02
07
0*
0.
03
08
1$
b0 "
b0 #
#2570
b1110 %
0(
1*
b1 #
#2580
1(
b1101 %
0,
0*
1.
b10 #
#2590
b1100 %
0(
1*
b11 #
#2600
1(
1,
b1011 %
01
0*
0.
13
b100 #
#2610
b1010 %
0(
1*
b101 #
#2620
1(
b1001 %
0,
0*
1.
b110 #
#2630
b1000 %
0(
1*
b111 #
#2640
1(
1,
11
b111 %
06
0*
0.
03
18
b1000 #
#2650
b110 %
0(
1*
b1001 #
#2660
1(
b101 %
0,
0*
1.
b1010 #
#2670
b100 %
0(
1*
b1011 #
#2680
1(
1,
b11 %
01
0*
0.
13
b1100 #
#2690
b10 %
0(
1*
b1101 #
#2700
1(
b1 %
0,
0*
1.
b1110 #
#2710
b0 %
0(
1*
b1111 #
#2720
05
09
00
04
0+
0,
01
b0 %
06
0/
b0 !
b0 &
0'
1)
0*
0.
03
08
b1 "
b0 #
#2730
16
15
11
19
10
1,
14
1+
b1111 %
1(
1/
b1111 !
b1111 &
1'
1*
b1 #
#2740
1,
b1110 %
0(
0/
b1110 !
b1110 &
0'
0*
1.
b10 #
#2750
0,
b1101 %
1(
1/
b1111 !
b1111 &
1'
1*
b11 #
#2760
04
0+
0,
11
b1100 %
0(
0/
b1100 !
b1100 &
0'
0*
0.
13
b100 #
#2770
01
1,
14
1+
b1011 %
1(
1/
b1111 !
b1111 &
1'
1*
b101 #
#2780
1,
b1010 %
0(
0/
b1110 !
b1110 &
0'
0*
1.
b110 #
#2790
0,
b1001 %
1(
1/
b1111 !
b1111 &
1'
1*
b111 #
#2800
09
00
04
0+
0,
01
16
b1000 %
0(
0/
b1000 !
b1000 &
0'
0*
0.
03
18
b1000 #
#2810
06
11
19
10
1,
14
1+
b111 %
1(
1/
b1111 !
b1111 &
1'
1*
b1001 #
#2820
1,
b110 %
0(
0/
b1110 !
b1110 &
0'
0*
1.
b1010 #
#2830
0,
b101 %
1(
1/
b1111 !
b1111 &
1'
1*
b1011 #
#2840
04
0+
0,
11
b100 %
0(
0/
b1100 !
b1100 &
0'
0*
0.
13
b1100 #
#2850
01
1,
14
1+
b11 %
1(
1/
b1111 !
b1111 &
1'
1*
b1101 #
#2860
1,
b10 %
0(
0/
b1110 !
b1110 &
0'
0*
1.
b1110 #
#2870
0,
b1 %
1(
1/
b1111 !
b1111 &
1'
1*
b1111 #
#2880
05
09
00
0,
01
06
04
b1 %
1(
1/
0+
b1 !
b1 &
1'
0)
1-
0*
0.
03
08
b10 "
b0 #
#2890
b0 %
0(
1*
b1 #
#2900
16
15
11
19
10
1(
b1111 %
1,
14
b1111 !
b1111 &
1+
0*
1.
b10 #
#2910
b1110 %
0(
1*
b11 #
#2920
1(
11
b1101 %
0,
04
b1101 !
b1101 &
0+
0*
0.
13
b100 #
#2930
b1100 %
0(
1*
b101 #
#2940
01
1(
b1011 %
1,
14
b1111 !
b1111 &
1+
0*
1.
b110 #
#2950
b1010 %
0(
1*
b111 #
#2960
09
00
1(
01
16
b1001 %
0,
04
b1001 !
b1001 &
0+
0*
0.
03
18
b1000 #
#2970
b1000 %
0(
1*
b1001 #
#2980
06
11
19
10
1(
b111 %
1,
14
b1111 !
b1111 &
1+
0*
1.
b1010 #
#2990
b110 %
0(
1*
b1011 #
#3000
1(
11
b101 %
0,
04
b1101 !
b1101 &
0+
0*
0.
13
b1100 #
#3010
b100 %
0(
1*
b1101 #
#3020
01
1(
b11 %
1,
14
b1111 !
b1111 &
1+
0*
1.
b1110 #
#3030
b10 %
0(
1*
b1111 #
#3040
05
09
00
01
06
0/
0'
b10 %
1,
04
b0 !
b0 &
0+
1)
0*
0.
03
08
b11 "
b0 #
#3050
0,
b1 %
1(
1/
b1 !
b1 &
1'
1*
b1 #
#3060
06
05
01
09
00
0(
0/
b0 %
0,
04
0'
b0 !
b0 &
0+
0*
1.
b10 #
#3070
16
15
11
19
10
14
1,
1+
b1111 %
1(
1/
b1111 !
b1111 &
1'
1*
b11 #
#3080
11
0(
0/
b1110 %
1,
04
0'
b1100 !
b1100 &
0+
0*
0.
13
b100 #
#3090
0,
b1101 %
1(
1/
b1101 !
b1101 &
1'
1*
b101 #
#3100
11
0(
0/
b1100 %
0,
04
0'
b1100 !
b1100 &
0+
0*
1.
b110 #
#3110
01
14
1,
1+
b1011 %
1(
1/
b1111 !
b1111 &
1'
1*
b111 #
#3120
09
00
01
16
0(
0/
b1010 %
1,
04
0'
b1000 !
b1000 &
0+
0*
0.
03
18
b1000 #
#3130
0,
b1001 %
1(
1/
b1001 !
b1001 &
1'
1*
b1001 #
#3140
16
01
09
00
0(
0/
b1000 %
0,
04
0'
b1000 !
b1000 &
0+
0*
1.
b1010 #
#3150
06
11
19
10
14
1,
1+
b111 %
1(
1/
b1111 !
b1111 &
1'
1*
b1011 #
#3160
11
0(
0/
b110 %
1,
04
0'
b1100 !
b1100 &
0+
0*
0.
13
b1100 #
#3170
0,
b101 %
1(
1/
b1101 !
b1101 &
1'
1*
b1101 #
#3180
11
0(
0/
b100 %
0,
04
0'
b1100 !
b1100 &
0+
0*
1.
b1110 #
#3190
01
14
1,
1+
b11 %
1(
1/
b1111 !
b1111 &
1'
1*
b1111 #
#3200
05
01
06
09
1(
1/
b11 %
1,
14
00
1'
b11 !
b11 &
1+
0)
0-
12
0*
0.
03
08
b100 "
b0 #
#3210
b10 %
0(
1*
b1 #
#3220
1(
b1 %
0,
0*
1.
b10 #
#3230
b0 %
0(
1*
b11 #
#3240
16
15
1(
1,
b1111 %
11
19
b1111 !
b1111 &
10
0*
0.
13
b100 #
#3250
b1110 %
0(
1*
b101 #
#3260
1(
b1101 %
0,
0*
1.
b110 #
#3270
b1100 %
0(
1*
b111 #
#3280
1(
1,
16
b1011 %
01
09
b1011 !
b1011 &
00
0*
0.
03
18
b1000 #
#3290
b1010 %
0(
1*
b1001 #
#3300
1(
b1001 %
0,
0*
1.
b1010 #
#3310
b1000 %
0(
1*
b1011 #
#3320
06
1(
1,
b111 %
11
19
b1111 !
b1111 &
10
0*
0.
13
b1100 #
#3330
b110 %
0(
1*
b1101 #
#3340
1(
b101 %
0,
0*
1.
b1110 #
#3350
b100 %
0(
1*
b1111 #
