邏輯設計實驗/一/LAB1/ripple.V
// module DFF with synchronous reset
module DFF (
    q,
    d,
    clk,
    reset
);

    output q;
    input d, clk, reset;
    reg q;

    always @(posedge reset or negedge clk)
        if (reset) q = 1'b0;
        else q = d;

endmodule

module TFF (
    q,
    clk,
    reset
);

    output q;
    input clk, reset;
    wire d;

    DFF dff0 (
        q,
        d,
        clk,
        reset
    );
    not n1 (d, q);  // not is a Verilog provided primitive.

endmodule

module ripple_carry_counter (
    q,
    clk,
    reset
);

    output [7:0] q;
    input clk, reset;

    //4 instances of the module TFF are created. 
    TFF tff0 (
        q[0],
        clk,
        reset
    );
    TFF tff1 (
        q[1],
        q[0],
        reset
    );
    TFF tff2 (
        q[2],
        q[1],
        reset
    );
    TFF tff3 (
        q[3],
        q[2],
        reset
    );
    TFF tff4 (
        q[4],
        q[3],
        reset
    );
    TFF tff5 (
        q[5],
        q[4],
        reset
    );
    TFF tff6 (
        q[6],
        q[5],
        reset
    );
    TFF tff7 (
        q[7],
        q[6],
        reset
    );


endmodule

邏輯設計實驗/一/LAB1/stimulus.v
module stimulus;

    reg clk, reset;
    wire [7:0] count;

    ripple_carry_counter c (
        count,
        clk,
        reset
    );

    initial clk = 1'b0;
    always #5 clk = ~clk;


    initial begin
        $dumpfile("test.vcd");
        $dumpvars(0, c);

        reset = 1'b1;

        #5 reset = 1'b0;
        #20 reset = 1'b1;
        #5 reset = 1'b0;

        #600 $finish;
    end

    // Monitor the outputs 
    initial $monitor($time, " Output count = %d", count);



endmodule

邏輯設計實驗/一/LAB1/test.vcd
$date
	Thu Sep 21 09:47:07 2023
$end
$version
	Icarus Verilog
$end
$timescale
	1s
$end
$scope module stimulus $end
$scope module c $end
$var wire 1 ! clk $end
$var wire 1 " reset $end
$var wire 8 # q [7:0] $end
$scope module tff0 $end
$var wire 1 ! clk $end
$var wire 1 $ d $end
$var wire 1 " reset $end
$var wire 1 % q $end
$scope module dff0 $end
$var wire 1 ! clk $end
$var wire 1 $ d $end
$var wire 1 " reset $end
$var reg 1 % q $end
$upscope $end
$upscope $end
$scope module tff1 $end
$var wire 1 & clk $end
$var wire 1 ' d $end
$var wire 1 " reset $end
$var wire 1 ( q $end
$scope module dff0 $end
$var wire 1 & clk $end
$var wire 1 ' d $end
$var wire 1 " reset $end
$var reg 1 ( q $end
$upscope $end
$upscope $end
$scope module tff2 $end
$var wire 1 ) clk $end
$var wire 1 * d $end
$var wire 1 " reset $end
$var wire 1 + q $end
$scope module dff0 $end
$var wire 1 ) clk $end
$var wire 1 * d $end
$var wire 1 " reset $end
$var reg 1 + q $end
$upscope $end
$upscope $end
$scope module tff3 $end
$var wire 1 , clk $end
$var wire 1 - d $end
$var wire 1 " reset $end
$var wire 1 . q $end
$scope module dff0 $end
$var wire 1 , clk $end
$var wire 1 - d $end
$var wire 1 " reset $end
$var reg 1 . q $end
$upscope $end
$upscope $end
$scope module tff4 $end
$var wire 1 / clk $end
$var wire 1 0 d $end
$var wire 1 " reset $end
$var wire 1 1 q $end
$scope module dff0 $end
$var wire 1 / clk $end
$var wire 1 0 d $end
$var wire 1 " reset $end
$var reg 1 1 q $end
$upscope $end
$upscope $end
$scope module tff5 $end
$var wire 1 2 clk $end
$var wire 1 3 d $end
$var wire 1 " reset $end
$var wire 1 4 q $end
$scope module dff0 $end
$var wire 1 2 clk $end
$var wire 1 3 d $end
$var wire 1 " reset $end
$var reg 1 4 q $end
$upscope $end
$upscope $end
$scope module tff6 $end
$var wire 1 5 clk $end
$var wire 1 6 d $end
$var wire 1 " reset $end
$var wire 1 7 q $end
$scope module dff0 $end
$var wire 1 5 clk $end
$var wire 1 6 d $end
$var wire 1 " reset $end
$var reg 1 7 q $end
$upscope $end
$upscope $end
$scope module tff7 $end
$var wire 1 8 clk $end
$var wire 1 9 d $end
$var wire 1 " reset $end
$var wire 1 : q $end
$scope module dff0 $end
$var wire 1 8 clk $end
$var wire 1 9 d $end
$var wire 1 " reset $end
$var reg 1 : q $end
$upscope $end
$upscope $end
$upscope $end
$upscope $end
$enddefinitions $end
$comment Show the parameter values. $end
$dumpall
$end
#0
$dumpvars
0:
19
08
07
16
05
04
13
02
01
10
0/
0.
1-
0,
0+
1*
0)
0(
1'
0&
0%
1$
b0 #
1"
0!
$end
#5
0"
1!
#10
0$
1&
b1 #
1%
0!
#15
1!
#20
0'
1)
1(
1$
0&
b10 #
0%
0!
#25
1'
0)
b0 #
0(
1!
1"
#30
0$
1&
b1 #
1%
0!
0"
#35
1!
#40
0'
1)
1(
1$
0&
b10 #
0%
0!
#45
1!
#50
0$
1&
b11 #
1%
0!
#55
1!
#60
0*
1,
1+
1'
0)
0(
1$
0&
b100 #
0%
0!
#65
1!
#70
0$
1&
b101 #
1%
0!
#75
1!
#80
0'
1)
1(
1$
0&
b110 #
0%
0!
#85
1!
#90
0$
1&
b111 #
1%
0!
#95
1!
#100
0-
1/
1.
1*
0,
0+
1'
0)
0(
1$
0&
b1000 #
0%
0!
#105
1!
#110
0$
1&
b1001 #
1%
0!
#115
1!
#120
0'
1)
1(
1$
0&
b1010 #
0%
0!
#125
1!
#130
0$
1&
b1011 #
1%
0!
#135
1!
#140
0*
1,
1+
1'
0)
0(
1$
0&
b1100 #
0%
0!
#145
1!
#150
0$
1&
b1101 #
1%
0!
#155
1!
#160
0'
1)
1(
1$
0&
b1110 #
0%
0!
#165
1!
#170
0$
1&
b1111 #
1%
0!
#175
1!
#180
00
12
11
1-
0/
0.
1*
0,
0+
1'
0)
0(
1$
0&
b10000 #
0%
0!
#185
1!
#190
0$
1&
b10001 #
1%
0!
#195
1!
#200
0'
1)
1(
1$
0&
b10010 #
0%
0!
#205
1!
#210
0$
1&
b10011 #
1%
0!
#215
1!
#220
0*
1,
1+
1'
0)
0(
1$
0&
b10100 #
0%
0!
#225
1!
#230
0$
1&
b10101 #
1%
0!
#235
1!
#240
0'
1)
1(
1$
0&
b10110 #
0%
0!
#245
1!
#250
0$
1&
b10111 #
1%
0!
#255
1!
#260
0-
1/
1.
1*
0,
0+
1'
0)
0(
1$
0&
b11000 #
0%
0!
#265
1!
#270
0$
1&
b11001 #
1%
0!
#275
1!
#280
0'
1)
1(
1$
0&
b11010 #
0%
0!
#285
1!
#290
0$
1&
b11011 #
1%
0!
#295
1!
#300
0*
1,
1+
1'
0)
0(
1$
0&
b11100 #
0%
0!
#305
1!
#310
0$
1&
b11101 #
1%
0!
#315
1!
#320
0'
1)
1(
1$
0&
b11110 #
0%
0!
#325
1!
#330
0$
1&
b11111 #
1%
0!
#335
1!
#340
03
15
14
10
02
01
1-
0/
0.
1*
0,
0+
1'
0)
0(
1$
0&
b100000 #
0%
0!
#345
1!
#350
0$
1&
b100001 #
1%
0!
#355
1!
#360
0'
1)
1(
1$
0&
b100010 #
0%
0!
#365
1!
#370
0$
1&
b100011 #
1%
0!
#375
1!
#380
0*
1,
1+
1'
0)
0(
1$
0&
b100100 #
0%
0!
#385
1!
#390
0$
1&
b100101 #
1%
0!
#395
1!
#400
0'
1)
1(
1$
0&
b100110 #
0%
0!
#405
1!
#410
0$
1&
b100111 #
1%
0!
#415
1!
#420
0-
1/
1.
1*
0,
0+
1'
0)
0(
1$
0&
b101000 #
0%
0!
#425
1!
#430
0$
1&
b101001 #
1%
0!
#435
1!
#440
0'
1)
1(
1$
0&
b101010 #
0%
0!
#445
1!
#450
0$
1&
b101011 #
1%
0!
#455
1!
#460
0*
1,
1+
1'
0)
0(
1$
0&
b101100 #
0%
0!
#465
1!
#470
0$
1&
b101101 #
1%
0!
#475
1!
#480
0'
1)
1(
1$
0&
b101110 #
0%
0!
#485
1!
#490
0$
1&
b101111 #
1%
0!
#495
1!
#500
00
12
11
1-
0/
0.
1*
0,
0+
1'
0)
0(
1$
0&
b110000 #
0%
0!
#505
1!
#510
0$
1&
b110001 #
1%
0!
#515
1!
#520
0'
1)
1(
1$
0&
b110010 #
0%
0!
#525
1!
#530
0$
1&
b110011 #
1%
0!
#535
1!
#540
0*
1,
1+
1'
0)
0(
1$
0&
b110100 #
0%
0!
#545
1!
#550
0$
1&
b110101 #
1%
0!
#555
1!
#560
0'
1)
1(
1$
0&
b110110 #
0%
0!
#565
1!
#570
0$
1&
b110111 #
1%
0!
#575
1!
#580
0-
1/
1.
1*
0,
0+
1'
0)
0(
1$
0&
b111000 #
0%
0!
#585
1!
#590
0$
1&
b111001 #
1%
0!
#595
1!
#600
0'
1)
1(
1$
0&
b111010 #
0%
0!
#605
1!
#610
0$
1&
b111011 #
1%
0!
#615
1!
#620
0*
1,
1+
1'
0)
0(
1$
0&
b111100 #
0%
0!
#625
1!
#630
0$
1&
b111101 #
1%
0!
