邏輯設計實驗/一/LAB6/alu.v
module alu (
    clk,
    a,
    b,
    c,
    sel,
    result
);

    input clk;
    input [3:0] a;
    input [3:0] b;
    input [3:0] c;
    input [2:0] sel;
    output [4:0] result;
    reg [4:0] r;

    always @(posedge clk) begin
        case (sel)
            3'b000: r <= (a > b && a > c) ? a : (b > a && b > c) ? b : c;
            3'b001: r <= a + b;
            3'b010: r <= a - b;
            3'b011: r <= a / b;
            3'b100: r <= a % b;
            3'b101: r <= a << 1;
            3'b110: r <= a >> 1;
            3'b111: r <= a > b;
        endcase
    end

    assign result = r;

endmodule

邏輯設計實驗/一/LAB6/stimulus.v
module stimulus;
    reg clk;
    always begin
        clk = 0;
        #5;
        clk = 1;
        #5;
    end
    wire [7:0] count;


    alu alu (
        clk,
        5,
        7,
        1,
        i,
        result
    );


    integer i;
    initial begin
        $dumpfile("test.vcd");
        $dumpvars(0, alu);
        #5 i = 0;
        #10 i = 7;
        #10 i = 4;
        #10 i = 5;
        #10 i = 3;
        #10 i = 2;
        #10 i = 1;
        #10 i = 6;
        #10;
        $finish;

    end



endmodule

邏輯設計實驗/一/LAB6/test.vcd
$date
	Sun Dec 24 00:17:11 2023
$end
$version
	Icarus Verilog
$end
$timescale
	1s
$end
$scope module stimulus $end
$scope module alu $end
$var wire 4 ! a [3:0] $end
$var wire 4 " b [3:0] $end
$var wire 4 # c [3:0] $end
$var wire 1 $ clk $end
$var wire 5 % result [4:0] $end
$var wire 3 & sel [2:0] $end
$var reg 5 ' r [4:0] $end
$upscope $end
$upscope $end
$enddefinitions $end
$comment Show the parameter values. $end
$dumpall
$end
#0
$dumpvars
bx '
bx &
bx %
0$
b1 #
b111 "
b101 !
$end
#5
b0 &
1$
#10
0$
#15
b0 %
b0 '
b111 &
1$
#20
0$
#25
b101 %
b101 '
b100 &
1$
#30
0$
#35
b1010 %
b1010 '
b101 &
1$
#40
0$
#45
b0 %
b0 '
b11 &
1$
#50
0$
#55
b11110 %
b11110 '
b10 &
1$
#60
0$
#65
b1100 %
b1100 '
b1 &
1$
#70
0$
#75
b10 %
b10 '
b110 &
1$
