lab_03/part2/RCA.v
module RCA (
    a,
    b,
    sum
);
    input [3:0] a, b;
    output [3:0] sum;
    wire [4:0] c;
    assign c   = a + b;
    assign sum = c[3:0];
endmodule

lab_03/part2/TM.v
`timescale 1ns / 1ps
module TM;

    reg [3:0] a, b;
    wire [3:0] sum;
    wire cor;
    integer i, j;

    assign cor = (i + j) % 16 == {sum};
    initial begin
        $dumpfile("test.vcd");
        $dumpvars(0, rca);
        $monitor("a = %d, b = %d | sum = %d | correct!! = %b", a, b, sum, cor);
        for (i = 0; i < 16; i = i + 1) begin
            a <= i;
            for (j = 0; j < 16; j = j + 1) begin
                b <= j;
                #10;
            end

        end
        $finish;

    end
    RCA rca (
        a,
        b,
        sum
    );
endmodule

lab_03/part2/test.vcd
$date
	Fri Apr 14 16:13:40 2023
$end
$version
	Icarus Verilog
$end
$timescale
	1ps
$end
$scope module TM $end
$scope module rca $end
$var wire 4 ! a [3:0] $end
$var wire 4 " b [3:0] $end
$var wire 4 # sum [3:0] $end
$var wire 5 $ c [4:0] $end
$upscope $end
$upscope $end
$enddefinitions $end
$comment Show the parameter values. $end
$dumpall
$end
#0
$dumpvars
b0 $
b0 #
b0 "
b0 !
$end
#10000
b1 #
b1 $
b1 "
#20000
b10 #
b10 $
b10 "
#30000
b11 #
b11 $
b11 "
#40000
b100 #
b100 $
b100 "
#50000
b101 #
b101 $
b101 "
#60000
b110 #
b110 $
b110 "
#70000
b111 #
b111 $
b111 "
#80000
b1000 #
b1000 $
b1000 "
#90000
b1001 #
b1001 $
b1001 "
#100000
b1010 #
b1010 $
b1010 "
#110000
b1011 #
b1011 $
b1011 "
#120000
b1100 #
b1100 $
b1100 "
#130000
b1101 #
b1101 $
b1101 "
#140000
b1110 #
b1110 $
b1110 "
#150000
b1111 #
b1111 $
b1111 "
#160000
b1 #
b0 "
b1 $
b1 !
#170000
b10 #
b10 $
b1 "
#180000
b11 #
b11 $
b10 "
#190000
b100 #
b100 $
b11 "
#200000
b101 #
b101 $
b100 "
#210000
b110 #
b110 $
b101 "
#220000
b111 #
b111 $
b110 "
#230000
b1000 #
b1000 $
b111 "
#240000
b1001 #
b1001 $
b1000 "
#250000
b1010 #
b1010 $
b1001 "
#260000
b1011 #
b1011 $
b1010 "
#270000
b1100 #
b1100 $
b1011 "
#280000
b1101 #
b1101 $
b1100 "
#290000
b1110 #
b1110 $
b1101 "
#300000
b1111 #
b1111 $
b1110 "
#310000
b0 #
b10000 $
b1111 "
#320000
b10 #
b0 "
b10 $
b10 !
#330000
b11 #
b11 $
b1 "
#340000
b100 #
b100 $
b10 "
#350000
b101 #
b101 $
b11 "
#360000
b110 #
b110 $
b100 "
#370000
b111 #
b111 $
b101 "
#380000
b1000 #
b1000 $
b110 "
#390000
b1001 #
b1001 $
b111 "
#400000
b1010 #
b1010 $
b1000 "
#410000
b1011 #
b1011 $
b1001 "
#420000
b1100 #
b1100 $
b1010 "
#430000
b1101 #
b1101 $
b1011 "
#440000
b1110 #
b1110 $
b1100 "
#450000
b1111 #
b1111 $
b1101 "
#460000
b0 #
b10000 $
b1110 "
#470000
b1 #
b10001 $
b1111 "
#480000
b11 #
b0 "
b11 $
b11 !
#490000
b100 #
b100 $
b1 "
#500000
b101 #
b101 $
b10 "
#510000
b110 #
b110 $
b11 "
#520000
b111 #
b111 $
b100 "
#530000
b1000 #
b1000 $
b101 "
#540000
b1001 #
b1001 $
b110 "
#550000
b1010 #
b1010 $
b111 "
#560000
b1011 #
b1011 $
b1000 "
#570000
b1100 #
b1100 $
b1001 "
#580000
b1101 #
b1101 $
b1010 "
#590000
b1110 #
b1110 $
b1011 "
#600000
b1111 #
b1111 $
b1100 "
#610000
b0 #
b10000 $
b1101 "
#620000
b1 #
b10001 $
b1110 "
#630000
b10 #
b10010 $
b1111 "
#640000
b100 #
b0 "
b100 $
b100 !
#650000
b101 #
b101 $
b1 "
#660000
b110 #
b110 $
b10 "
#670000
b111 #
b111 $
b11 "
#680000
b1000 #
b1000 $
b100 "
#690000
b1001 #
b1001 $
b101 "
#700000
b1010 #
b1010 $
b110 "
#710000
b1011 #
b1011 $
b111 "
#720000
b1100 #
b1100 $
b1000 "
#730000
b1101 #
b1101 $
b1001 "
#740000
b1110 #
b1110 $
b1010 "
#750000
b1111 #
b1111 $
b1011 "
#760000
b0 #
b10000 $
b1100 "
#770000
b1 #
b10001 $
b1101 "
#780000
b10 #
b10010 $
b1110 "
#790000
b11 #
b10011 $
b1111 "
#800000
b101 #
b0 "
b101 $
b101 !
#810000
b110 #
b110 $
b1 "
#820000
b111 #
b111 $
b10 "
#830000
b1000 #
b1000 $
b11 "
#840000
b1001 #
b1001 $
b100 "
#850000
b1010 #
b1010 $
b101 "
#860000
b1011 #
b1011 $
b110 "
#870000
b1100 #
b1100 $
b111 "
#880000
b1101 #
b1101 $
b1000 "
#890000
b1110 #
b1110 $
b1001 "
#900000
b1111 #
b1111 $
b1010 "
#910000
b0 #
b10000 $
b1011 "
#920000
b1 #
b10001 $
b1100 "
#930000
b10 #
b10010 $
b1101 "
#940000
b11 #
b10011 $
b1110 "
#950000
b100 #
b10100 $
b1111 "
#960000
b110 #
b0 "
b110 $
b110 !
#970000
b111 #
b111 $
b1 "
#980000
b1000 #
b1000 $
b10 "
#990000
b1001 #
b1001 $
b11 "
#1000000
b1010 #
b1010 $
b100 "
#1010000
b1011 #
b1011 $
b101 "
#1020000
b1100 #
b1100 $
b110 "
#1030000
b1101 #
b1101 $
b111 "
#1040000
b1110 #
b1110 $
b1000 "
#1050000
b1111 #
b1111 $
b1001 "
#1060000
b0 #
b10000 $
b1010 "
#1070000
b1 #
b10001 $
b1011 "
#1080000
b10 #
b10010 $
b1100 "
#1090000
b11 #
b10011 $
b1101 "
#1100000
b100 #
b10100 $
b1110 "
#1110000
b101 #
b10101 $
b1111 "
#1120000
b111 #
b0 "
b111 $
b111 !
#1130000
b1000 #
b1000 $
b1 "
#1140000
b1001 #
b1001 $
b10 "
#1150000
b1010 #
b1010 $
b11 "
#1160000
b1011 #
b1011 $
b100 "
#1170000
b1100 #
b1100 $
b101 "
#1180000
b1101 #
b1101 $
b110 "
#1190000
b1110 #
b1110 $
b111 "
#1200000
b1111 #
b1111 $
b1000 "
#1210000
b0 #
b10000 $
b1001 "
#1220000
b1 #
b10001 $
b1010 "
#1230000
b10 #
b10010 $
b1011 "
#1240000
b11 #
b10011 $
b1100 "
#1250000
b100 #
b10100 $
b1101 "
#1260000
b101 #
b10101 $
b1110 "
#1270000
b110 #
b10110 $
b1111 "
#1280000
b1000 #
b0 "
b1000 $
b1000 !
#1290000
b1001 #
b1001 $
b1 "
#1300000
b1010 #
b1010 $
b10 "
#1310000
b1011 #
b1011 $
b11 "
#1320000
b1100 #
b1100 $
b100 "
#1330000
b1101 #
b1101 $
b101 "
#1340000
b1110 #
b1110 $
b110 "
#1350000
b1111 #
b1111 $
b111 "
#1360000
b0 #
b10000 $
b1000 "
#1370000
b1 #
b10001 $
b1001 "
#1380000
b10 #
b10010 $
b1010 "
#1390000
b11 #
b10011 $
b1011 "
#1400000
b100 #
b10100 $
b1100 "
#1410000
b101 #
b10101 $
b1101 "
#1420000
b110 #
b10110 $
b1110 "
#1430000
b111 #
b10111 $
b1111 "
#1440000
b1001 #
b0 "
b1001 $
b1001 !
#1450000
b1010 #
b1010 $
b1 "
#1460000
b1011 #
b1011 $
b10 "
#1470000
b1100 #
b1100 $
b11 "
#1480000
b1101 #
b1101 $
b100 "
#1490000
b1110 #
b1110 $
b101 "
#1500000
b1111 #
b1111 $
b110 "
#1510000
b0 #
b10000 $
b111 "
#1520000
b1 #
b10001 $
b1000 "
#1530000
b10 #
b10010 $
b1001 "
#1540000
b11 #
b10011 $
b1010 "
#1550000
b100 #
b10100 $
b1011 "
#1560000
b101 #
b10101 $
b1100 "
#1570000
b110 #
b10110 $
b1101 "
#1580000
b111 #
b10111 $
b1110 "
#1590000
b1000 #
b11000 $
b1111 "
#1600000
b1010 #
b0 "
b1010 $
b1010 !
#1610000
b1011 #
b1011 $
b1 "
#1620000
b1100 #
b1100 $
b10 "
#1630000
b1101 #
b1101 $
b11 "
#1640000
b1110 #
b1110 $
b100 "
#1650000
b1111 #
b1111 $
b101 "
#1660000
b0 #
b10000 $
b110 "
#1670000
b1 #
b10001 $
b111 "
#1680000
b10 #
b10010 $
b1000 "
#1690000
b11 #
b10011 $
b1001 "
#1700000
b100 #
b10100 $
b1010 "
#1710000
b101 #
b10101 $
b1011 "
#1720000
b110 #
b10110 $
b1100 "
#1730000
b111 #
b10111 $
b1101 "
#1740000
b1000 #
b11000 $
b1110 "
#1750000
b1001 #
b11001 $
b1111 "
#1760000
b1011 #
b0 "
b1011 $
b1011 !
#1770000
b1100 #
b1100 $
b1 "
#1780000
b1101 #
b1101 $
b10 "
#1790000
b1110 #
b1110 $
b11 "
#1800000
b1111 #
b1111 $
b100 "
#1810000
b0 #
b10000 $
b101 "
#1820000
b1 #
b10001 $
b110 "
#1830000
b10 #
b10010 $
b111 "
#1840000
b11 #
b10011 $
b1000 "
#1850000
b100 #
b10100 $
b1001 "
#1860000
b101 #
b10101 $
b1010 "
#1870000
b110 #
b10110 $
b1011 "
#1880000
b111 #
b10111 $
b1100 "
#1890000
b1000 #
b11000 $
b1101 "
#1900000
b1001 #
b11001 $
b1110 "
#1910000
b1010 #
b11010 $
b1111 "
#1920000
b1100 #
b0 "
b1100 $
b1100 !
#1930000
b1101 #
b1101 $
b1 "
#1940000
b1110 #
b1110 $
b10 "
#1950000
b1111 #
b1111 $
b11 "
#1960000
b0 #
b10000 $
b100 "
#1970000
b1 #
b10001 $
b101 "
#1980000
b10 #
b10010 $
b110 "
#1990000
b11 #
b10011 $
b111 "
#2000000
b100 #
b10100 $
b1000 "
#2010000
b101 #
b10101 $
b1001 "
#2020000
b110 #
b10110 $
b1010 "
#2030000
b111 #
b10111 $
b1011 "
#2040000
b1000 #
b11000 $
b1100 "
#2050000
b1001 #
b11001 $
b1101 "
#2060000
b1010 #
b11010 $
b1110 "
#2070000
b1011 #
b11011 $
b1111 "
#2080000
b1101 #
b0 "
b1101 $
b1101 !
#2090000
b1110 #
b1110 $
b1 "
#2100000
b1111 #
b1111 $
b10 "
#2110000
b0 #
b10000 $
b11 "
#2120000
b1 #
b10001 $
b100 "
#2130000
b10 #
b10010 $
b101 "
#2140000
b11 #
b10011 $
b110 "
#2150000
b100 #
b10100 $
b111 "
#2160000
b101 #
b10101 $
b1000 "
#2170000
b110 #
b10110 $
b1001 "
#2180000
b111 #
b10111 $
b1010 "
#2190000
b1000 #
b11000 $
b1011 "
#2200000
b1001 #
b11001 $
b1100 "
#2210000
b1010 #
b11010 $
b1101 "
#2220000
b1011 #
b11011 $
b1110 "
#2230000
b1100 #
b11100 $
b1111 "
#2240000
b1110 #
b0 "
b1110 $
b1110 !
#2250000
b1111 #
b1111 $
b1 "
#2260000
b0 #
b10000 $
b10 "
#2270000
b1 #
b10001 $
b11 "
#2280000
b10 #
b10010 $
b100 "
#2290000
b11 #
b10011 $
b101 "
#2300000
b100 #
b10100 $
b110 "
#2310000
b101 #
b10101 $
b111 "
#2320000
b110 #
b10110 $
b1000 "
#2330000
b111 #
b10111 $
b1001 "
#2340000
b1000 #
b11000 $
b1010 "
#2350000
b1001 #
b11001 $
b1011 "
#2360000
b1010 #
b11010 $
b1100 "
#2370000
b1011 #
b11011 $
b1101 "
#2380000
b1100 #
b11100 $
b1110 "
#2390000
b1101 #
b11101 $
b1111 "
#2400000
b1111 #
b0 "
b1111 $
b1111 !
#2410000
b0 #
b10000 $
b1 "
#2420000
b1 #
b10001 $
b10 "
#2430000
b10 #
b10010 $
b11 "
#2440000
b11 #
b10011 $
b100 "
#2450000
b100 #
b10100 $
b101 "
#2460000
b101 #
b10101 $
b110 "
#2470000
b110 #
b10110 $
b111 "
#2480000
b111 #
b10111 $
b1000 "
#2490000
b1000 #
b11000 $
b1001 "
#2500000
b1001 #
b11001 $
b1010 "
#2510000
b1010 #
b11010 $
b1011 "
#2520000
b1011 #
b11011 $
b1100 "
#2530000
b1100 #
b11100 $
b1101 "
#2540000
b1101 #
b11101 $
b1110 "
#2550000
b1110 #
b11110 $
b1111 "
